Code/execute.v
/*
	Module written by Rahul Kejriwal
	CS14B023
	Synchronous module for execution and result storage 
*/

module executeAndStoreBack(
		input clk,
		input rst,

		input[ 3:0] opcode,
		input[ 3:0] destReg,
		input[15:0] srcVal1,
		input[15:0] srcVal2,
		input[ 7:0] memAddr, 
		input used1,
		input used2,

		output[ 3:0] destRegStore,
		output[15:0] destVal,
		output storeNow,
		input storeDone,

		output[ 7:0] memAddrLoadStore,
		output[15:0] memValueStore,

		input[15:0] memValueLoad,
		input valueReady,
		output readReq,
		output writeReq,

		output[15:0] ProcessorStatusWord,
	
		output powerdown
	);

	reg[ 3:0] destRegStore;
	reg[ 7:0] memAddrLoadStore;
	reg[15:0] destVal, memValueStore;

	reg[15:0] LastComputedValue;
	reg[15:0] ProcessorStatusWord;

	reg readReq, storeNow, writeReq;
	reg[15:0] val1, val2;
	reg powerdown;

	initial begin
		destRegStore 		= 4'b0;
		memAddrLoadStore	= 8'b0;
		memValueStore		= 16'b0;
		destVal				= 16'b0;
		
		LastComputedValue   = 16'b0;
		ProcessorStatusWord = 16'b0;		
		
		readReq = 0;
		storeNow = 0;
		val1 = 16'b0;
		val2 = 16'b0;
		powerdown = 0;
	end

	always @(posedge rst) begin
		destRegStore 		= 4'b0;
		memAddrLoadStore	= 8'b0;
		memValueStore		= 16'b0;
		destVal		        = 16'b0;
		
		LastComputedValue   = 16'b0;
		ProcessorStatusWord = 16'b0;
		
		readReq = 0;
		storeNow = 0;
		val1 = 16'b0;
		val2 = 16'b0;
	end

	always @(posedge clk) begin
		// Write Sync Signal for register writes
		storeNow = 0;
		writeReq = 0;
		
		#1
		ProcessorStatusWord = 16'b0;

		// Checking if src1 was being computed
		#1 if(used1)
			val1 = LastComputedValue;
		else
			val1 = srcVal1;			

		// Checking if src2 was being computed
		if(used2)
			val2 = LastComputedValue;
		else
			val2 = srcVal2;			

		// Execute appropriate action for the opcode
		#0 case(opcode)
			// NOP
			 0: begin
			 		// Doing nothing
			 		$display("Doing nothing");
			 	end 

			// HLT
			 1: begin
			 		$display("HLTing");
			 		powerdown = 1;
			 	end

			// ADD
			 2: begin
			        {ProcessorStatusWord[15],destVal} = val1 + val2;
				 	
				    if(val1[15] == val2[15] && destVal[15] != val1[15])  //checking for overflow in addition
			 			ProcessorStatusWord[14] = 1;
			 	end

			// SUB
			 3: begin
				 	{ProcessorStatusWord[15],destVal} = val1 - val2;
				 	
				    if(val1[15] != val2[15] && destVal[15] != val1[15])   //checking for overflow in substraction
				 		ProcessorStatusWord[14] = 1;
			 	end 
			 
			// MUL
			 4: begin
				 	{ProcessorStatusWord[15],destVal} = val1 * val2;
				 							 	
			 	end

			// SL
			 5: begin
				 	{ProcessorStatusWord[15],destVal} = val1 << val2;		 	
			 	end

			// SR
			 6: begin
			 		{ProcessorStatusWord[15],destVal} = val1 >> val2;
			 	end
			 
			// AND
			 7: begin
			 		destVal = val1 & val2;
			 	end

			// OR
			 8: begin
			 		destVal = val1 | val2;
			 	end
			 
			// NOT
			 9: begin
			 		// ignores val2
				 	destVal = ~val1;
				end
			
			// XOR
			10: begin
					destVal = val1 ^ val2;
				end

			// LOAD
			14: begin
					memAddrLoadStore = memAddr;    //storing memory address to memAddrLoadStore register
					readReq = 1'b1;                //sending a read request to memory
				end

			// STORE
			15: begin
					memAddrLoadStore = memAddr;
					memValueStore = val1;          //storing the value to be stored in memValueStore
					writeReq = 1;                  //sending a write request to memory
				end

			default:begin
						$display("Failure in execute unit!");
						powerdown = 1;
					end
		endcase

		// Set register address to write to and send signal to write to reg file
		if(opcode >= 2 && opcode <= 10) begin
			//storing the dest reg address to destRegStore
			destRegStore = destReg;
			//sending storenow signal to regfile unit
			storeNow = 1;

		 	if({ProcessorStatusWord[14], destVal} == 0)    	//checking whether the computed value was zero or not
				ProcessorStatusWord[13] = 1;	        	//setting the zero status flag bit to 1
			
			#1 LastComputedValue = destVal;
		end
	end

	// Sent signal to read mem location. Waiting for signal that value is ready.
	always @(posedge valueReady) begin
		readReq = 1'b0;
		
		//getting the value loaded from memory into destVal
		destVal = memValueLoad;
		if(destVal == 0)              						//checking whether the computed value was zero or not
			ProcessorStatusWord[13] = 1;	                //setting the zero status flag bit to 1
	        
		
		//storing the loaded value into the destination register
		destRegStore = destReg;
		storeNow = 1;			
		#1 LastComputedValue = destVal;
	end

endmodule

Testbench/execute_testbench.v
/*
	Module written by Debanjan Ghatak
	CS16S033

	Execution unit test bench
*/

`include "/home/debanjan/Desktop/DDV_pro/3-Stage-Pipeline/Code/execute.v"

module execute_TestBench(
		output clk,
		output rst,

		output[ 3:0] opcode,
		output[ 3:0] destReg,
		output[15:0] srcVal1,
		output[15:0] srcVal2,
		output[ 7:0] memAddr, 
		output used1,
		output used2,

		input[ 3:0] destRegStore,
		input[15:0] destVal,
		input storeNow,
		output storeDone,

		input[ 7:0] memAddrLoadStore,
		input[15:0] memValueStore,

		output[15:0] memValueLoad,
		output valueReady,
		input readReq,
		input writeReq,

		input[15:0] ProcessorStatusWord,
	
		input powerdown
	);

	reg clk, rst;
	reg[ 3:0] opcode;
 	reg[ 3:0] destReg;
	reg[15:0] srcVal1;
	reg[15:0] srcVal2;
	reg[ 7:0] memAddr;
	reg used1;
	reg used2, storeDone, valueReady;
	reg[15:0] memValueLoad;

	executeAndStoreBack E(clk, rst, opcode, destReg, srcVal1, srcVal2, memAddr, used1, used2, destRegStore, destVal, storeNow, storeDone, memAddrLoadStore, memValueStore, memValueLoad, valueReady, readReq, writeReq, ProcessorStatusWord, powerdown);

	always begin
		#3 clk = ~clk;
	end

	initial begin
		$dumpfile("execute.vcd");
    	$dumpvars(0,execute_TestBench);

	clk=0;
	rst=0;

	$monitor($time,, "clk: %b, opcode: %b, destReg: %b, srcVal1: %b ,srcVal2: %b,memAddr: %b,used1: %b,used2:,destRegStore: %b,destVal: %b,storeNow: %b,storeDone: %b,memAddrLoadStore: %b,memValueStore: %b,memValueLoad: %b,valueReady: %b,readReq: %b, writeReq: %b,ProcessorStatusWord: %b,powerdown: %b", clk, opcode, destReg, srcVal1, srcVal2, memAddr, used1, used2, destRegStore, destVal, storeNow, storeDone, memAddrLoadStore, memValueStore, memValueLoad, valueReady, readReq, writeReq, ProcessorStatusWord, powerdown);

        #5
	opcode=2;
	srcVal1=24;
	srcVal2=30;
	destReg=12;
	used1=0;
	used2=0;
	
	#6
	opcode=3;
	srcVal1=25;
	srcVal2=9;
	destReg=13;
	used1=0;
	used2=0;

	#6
	opcode=5;
	srcVal1=24;
	srcVal2=5;
	destReg=11;
	used1=0;
	used2=0;

	#6
	opcode=7;
	srcVal1=56;
	srcVal2=32;
	destReg=5;
	used1=0;
	used2=0;

	#6
	opcode=9;
	srcVal1=11;
	destReg=14;
	used1=0;
	used2=0;

	#6
	opcode=15;
	memAddr=180;
	srcVal1=45;
	used1=0;
	used2=0;

	#6
	opcode=2;
	srcVal1=15;
	srcVal2=14;
	destReg=2;
	used1=1;
	used2=1;

	#6
	opcode=8;
	srcVal1=11;
	srcVal2=21;
	destReg=31;
	used1=0;
	used2=0;

	#6
	opcode=9;
	srcVal1=10;
	used1=1;
	used2=1;

	#6
	opcode=10;
	srcVal1=101;
	srcVal2=32;
	destReg=67;
	used1=0;
	used2=0;

	#6
	opcode=14;
	memAddr=26;
	
	#550 $finish;
       end
		
endmodule

Testbench/execute.vcd
$date
	Tue Feb 28 01:02:13 2017
$end
$version
	Icarus Verilog
$end
$timescale
	1s
$end
$scope module execute_TestBench $end
$var wire 16 ! ProcessorStatusWord [15:0] $end
$var wire 4 " destRegStore [3:0] $end
$var wire 16 # destVal [15:0] $end
$var wire 8 $ memAddrLoadStore [7:0] $end
$var wire 16 % memValueStore [15:0] $end
$var wire 1 & powerdown $end
$var wire 1 ' readReq $end
$var wire 1 ( storeNow $end
$var wire 1 ) writeReq $end
$var reg 1 * clk $end
$var reg 4 + destReg [3:0] $end
$var reg 8 , memAddr [7:0] $end
$var reg 16 - memValueLoad [15:0] $end
$var reg 4 . opcode [3:0] $end
$var reg 1 / rst $end
$var reg 16 0 srcVal1 [15:0] $end
$var reg 16 1 srcVal2 [15:0] $end
$var reg 1 2 storeDone $end
$var reg 1 3 used1 $end
$var reg 1 4 used2 $end
$var reg 1 5 valueReady $end
$scope module E $end
$var wire 1 6 clk $end
$var wire 4 7 destReg [3:0] $end
$var wire 8 8 memAddr [7:0] $end
$var wire 16 9 memValueLoad [15:0] $end
$var wire 4 : opcode [3:0] $end
$var wire 1 ; rst $end
$var wire 16 < srcVal1 [15:0] $end
$var wire 16 = srcVal2 [15:0] $end
$var wire 1 > storeDone $end
$var wire 1 ? used1 $end
$var wire 1 @ used2 $end
$var wire 1 A valueReady $end
$var reg 16 B LastComputedValue [15:0] $end
$var reg 16 C ProcessorStatusWord [15:0] $end
$var reg 4 D destRegStore [3:0] $end
$var reg 16 E destVal [15:0] $end
$var reg 8 F memAddrLoadStore [7:0] $end
$var reg 16 G memValueStore [15:0] $end
$var reg 1 H powerdown $end
$var reg 1 I readReq $end
$var reg 1 J storeNow $end
$var reg 16 K val1 [15:0] $end
$var reg 16 L val2 [15:0] $end
$var reg 1 M writeReq $end
$upscope $end
$upscope $end
$enddefinitions $end
#0
$dumpvars
xM
b0 L
b0 K
0J
0I
0H
b0 G
b0 F
b0 E
b0 D
b0 C
b0 B
xA
x@
x?
x>
bx =
bx <
0;
bx :
bx 9
bx 8
bx 7
06
x5
x4
x3
x2
bx 1
bx 0
0/
bx .
bx -
bx ,
bx +
0*
x)
0(
0'
0&
b0 %
b0 $
b0 #
b0 "
b0 !
$end
#3
0M
0)
1*
16
#5
1J
1(
b1100 D
b1100 "
b0 C
b110110 E
b110110 #
b11110 L
b11000 K
04
0@
03
0?
b1100 +
b1100 7
b11110 1
b11110 =
b11000 0
b11000 <
b10 .
b10 :
#6
b110110 B
0*
06
#9
0J
0(
1*
16
#11
1J
1(
b100 D
b100 "
b1000000000000000 C
b1000000000000000 !
b1011111111111111 E
b1011111111111111 #
b1111111111111111 L
b1100000000000000 K
b100 +
b100 7
b1111111111111111 1
b1111111111111111 =
b1100000000000000 0
b1100000000000000 <
#12
b1011111111111111 B
0*
06
#15
0J
0(
1*
16
#16
b0 C
b0 !
#17
1J
1(
b101 D
b101 "
b1100000000000000 C
b1100000000000000 !
b111111111111111 E
b111111111111111 #
b1000000000000000 L
b1111111111111111 K
b101 +
b101 7
b1000000000000000 1
b1000000000000000 =
b1111111111111111 0
b1111111111111111 <
#18
b111111111111111 B
0*
06
#21
0J
0(
1*
16
#22
b0 C
b0 !
#23
b10000000000000 !
1J
1(
b110 D
b110 "
b10000000000000 C
b0 E
b0 #
b0 L
b0 K
b110 +
b110 7
b0 1
b0 =
b0 0
b0 <
#24
b0 B
0*
06
#27
0J
0(
1*
16
#28
b0 C
b0 !
#29
1J
1(
b1101 D
b1101 "
b0 C
b10000 E
b10000 #
b1001 L
b11001 K
b1101 +
b1101 7
b1001 1
b1001 =
b11001 0
b11001 <
b11 .
b11 :
#30
b10000 B
0*
06
#33
0J
0(
1*
16
#35
1J
1(
b111 D
b111 "
b100000000000000 !
b100000000000000 C
b111111111001000 E
b111111111001000 #
b111000 L
b1000000000000000 K
b111 +
b111 7
b111000 1
b111000 =
b1000000000000000 0
b1000000000000000 <
#36
b111111111001000 B
0*
06
#39
0J
0(
1*
16
#40
b0 C
b0 !
#41
1J
1(
b1000 D
b1000 "
b100000000000000 !
b100000000000000 C
b111111111111111 E
b111111111111111 #
b1 L
b1000 +
b1000 7
b1 1
b1 =
#42
b111111111111111 B
0*
06
#45
0J
0(
1*
16
#46
b0 C
b0 !
#47
1J
1(
b1011 D
b1011 "
b0 C
b1100000000 E
b1100000000 #
b101 L
b11000 K
b1011 +
b1011 7
b101 1
b101 =
b11000 0
b11000 <
b101 .
b101 :
#48
b1100000000 B
0*
06
#51
0J
0(
1*
16
#53
1J
1(
b101 D
b101 "
b100000 E
b100000 #
b100000 L
b111000 K
b101 +
b101 7
b100000 1
b100000 =
b111000 0
b111000 <
b111 .
b111 :
#54
b100000 B
0*
06
#57
0J
0(
1*
16
#59
1J
1(
b1110 D
b1110 "
b1111111111110100 E
b1111111111110100 #
b1011 K
b1110 +
b1110 7
b1011 0
b1011 <
b1001 .
b1001 :
#60
b1111111111110100 B
0*
06
#63
0J
0(
1*
16
#65
1M
1)
b101101 G
b101101 %
b10110100 F
b10110100 $
b101101 K
b101101 0
b101101 <
b10110100 ,
b10110100 8
b1111 .
b1111 :
#66
0*
06
#69
0M
0)
1*
16
#71
1J
1(
b10 D
b10 "
b1000000000000000 C
b1000000000000000 !
b1111111111101000 E
b1111111111101000 #
b1111111111110100 L
b1111111111110100 K
14
1@
13
1?
b10 +
b10 7
b1110 1
b1110 =
b1111 0
b1111 <
b10 .
b10 :
#72
b1111111111101000 B
0*
06
#75
0J
0(
1*
16
#76
b0 C
b0 !
#77
1J
1(
b1111 D
b1111 "
b11111 E
b11111 #
b10101 L
b1011 K
04
0@
03
0?
b1111 +
b1111 7
b10101 1
b10101 =
b1011 0
b1011 <
b1000 .
b1000 :
#78
b11111 B
0*
06
#81
0J
0(
1*
16
#83
1J
1(
b1111111111100000 E
b1111111111100000 #
b11111 L
b11111 K
14
1@
13
1?
b1010 0
b1010 <
b1001 .
b1001 :
#84
b1111111111100000 B
0*
06
#87
0J
0(
1*
16
#89
1J
1(
b11 D
b11 "
b1000101 E
b1000101 #
b100000 L
b1100101 K
04
0@
03
0?
b11 +
b11 7
b100000 1
b100000 =
b1100101 0
b1100101 <
b1010 .
b1010 :
#90
b1000101 B
0*
06
#93
0J
0(
1*
16
#95
1I
1'
b11010 F
b11010 $
b0 +
b0 7
b11010 ,
b11010 8
b1110 .
b1110 :
#96
0*
06
#99
1*
16
#101
1M
1)
b1100010101 G
b1100010101 %
b101101 F
b101101 $
b1100010101 K
b1100010101 0
b1100010101 <
b101101 ,
b101101 8
b1111 .
b1111 :
#102
0*
06
#105
0M
0)
1*
16
#107
1M
1)
#108
0*
06
#111
0M
0)
1*
16
#113
1M
1)
#114
0*
06
#117
0M
0)
1*
16
#119
1M
1)
#120
0*
06
#123
0M
0)
1*
16
#125
1M
1)
#126
0*
06
#129
0M
0)
1*
16
#131
1M
1)
#132
0*
06
#135
0M
0)
1*
16
#137
1M
1)
#138
0*
06
#141
0M
0)
1*
16
#143
1M
1)
#144
0*
06
#147
0M
0)
1*
16
#149
1M
1)
#150
0*
06
#153
0M
0)
1*
16
#155
1M
1)
#156
0*
06
#159
0M
0)
1*
16
#161
1M
1)
#162
0*
06
#165
0M
0)
1*
16
#167
1M
1)
#168
0*
06
#171
0M
0)
1*
16
#173
1M
1)
#174
0*
06
#177
0M
0)
1*
16
#179
1M
1)
#180
0*
06
#183
0M
0)
1*
16
#185
1M
1)
#186
0*
06
#189
0M
0)
1*
16
#191
1M
1)
#192
0*
06
#195
0M
0)
1*
16
#197
1M
1)
#198
0*
06
#201
0M
0)
1*
16
#203
1M
1)
#204
0*
06
#207
0M
0)
1*
16
#209
1M
1)
#210
0*
06
#213
0M
0)
1*
16
#215
1M
1)
#216
0*
06
#219
0M
0)
1*
16
#221
1M
1)
#222
0*
06
#225
0M
0)
1*
16
#227
1M
1)
#228
0*
06
#231
0M
0)
1*
16
#233
1M
1)
#234
0*
06
#237
0M
0)
1*
16
#239
1M
1)
#240
0*
06
#243
0M
0)
1*
16
#245
1M
1)
#246
0*
06
#249
0M
0)
1*
16
#251
1M
1)
#252
0*
06
#255
0M
0)
1*
16
#257
1M
1)
#258
0*
06
#261
0M
0)
1*
16
#263
1M
1)
#264
0*
06
#267
0M
0)
1*
16
#269
1M
1)
#270
0*
06
#273
0M
0)
1*
16
#275
1M
1)
#276
0*
06
#279
0M
0)
1*
16
#281
1M
1)
#282
0*
06
#285
0M
0)
1*
16
#287
1M
1)
#288
0*
06
#291
0M
0)
1*
16
#293
1M
1)
#294
0*
06
#297
0M
0)
1*
16
#299
1M
1)
#300
0*
06
#303
0M
0)
1*
16
#305
1M
1)
#306
0*
06
#309
0M
0)
1*
16
#311
1M
1)
#312
0*
06
#315
0M
0)
1*
16
#317
1M
1)
#318
0*
06
#321
0M
0)
1*
16
#323
1M
1)
#324
0*
06
#327
0M
0)
1*
16
#329
1M
1)
#330
0*
06
#333
0M
0)
1*
16
#335
1M
1)
#336
0*
06
#339
0M
0)
1*
16
#341
1M
1)
#342
0*
06
#345
0M
0)
1*
16
#347
1M
1)
#348
0*
06
#351
0M
0)
1*
16
#353
1M
1)
#354
0*
06
#357
0M
0)
1*
16
#359
1M
1)
#360
0*
06
#363
0M
0)
1*
16
#365
1M
1)
#366
0*
06
#369
0M
0)
1*
16
#371
1M
1)
#372
0*
06
#375
0M
0)
1*
16
#377
1M
1)
#378
0*
06
#381
0M
0)
1*
16
#383
1M
1)
#384
0*
06
#387
0M
0)
1*
16
#389
1M
1)
#390
0*
06
#393
0M
0)
1*
16
#395
1M
1)
#396
0*
06
#399
0M
0)
1*
16
#401
1M
1)
#402
0*
06
#405
0M
0)
1*
16
#407
1M
1)
#408
0*
06
#411
0M
0)
1*
16
#413
1M
1)
#414
0*
06
#417
0M
0)
1*
16
#419
1M
1)
#420
0*
06
#423
0M
0)
1*
16
#425
1M
1)
#426
0*
06
#429
0M
0)
1*
16
#431
1M
1)
#432
0*
06
#435
0M
0)
1*
16
#437
1M
1)
#438
0*
06
#441
0M
0)
1*
16
#443
1M
1)
#444
0*
06
#447
0M
0)
1*
16
#449
1M
1)
#450
0*
06
#453
0M
0)
1*
16
#455
1M
1)
#456
0*
06
#459
0M
0)
1*
16
#461
1M
1)
#462
0*
06
#465
0M
0)
1*
16
#467
1M
1)
#468
0*
06
#471
0M
0)
1*
16
#473
1M
1)
#474
0*
06
#477
0M
0)
1*
16
#479
1M
1)
#480
0*
06
#483
0M
0)
1*
16
#485
1M
1)
#486
0*
06
#489
0M
0)
1*
16
#491
1M
1)
#492
0*
06
#495
0M
0)
1*
16
#497
1M
1)
#498
0*
06
#501
0M
0)
1*
16
#503
1M
1)
#504
0*
06
#507
0M
0)
1*
16
#509
1M
1)
#510
0*
06
#513
0M
0)
1*
16
#515
1M
1)
#516
0*
06
#519
0M
0)
1*
16
#521
1M
1)
#522
0*
06
#525
0M
0)
1*
16
#527
1M
1)
#528
0*
06
#531
0M
0)
1*
16
#533
1M
1)
#534
0*
06
#537
0M
0)
1*
16
#539
1M
1)
#540
0*
06
#543
0M
0)
1*
16
#545
1M
1)
#546
0*
06
#549
0M
0)
1*
16
#551
1M
1)
#552
0*
06
#555
0M
0)
1*
16
#557
1M
1)
#558
0*
06
#561
0M
0)
1*
16
#563
1M
1)
#564
0*
06
#567
0M
0)
1*
16
#569
1M
1)
#570
0*
06
#573
0M
0)
1*
16
#575
1M
1)
#576
0*
06
#579
0M
0)
1*
16
#581
1M
1)
#582
0*
06
#585
0M
0)
1*
16
#587
1M
1)
#588
0*
06
#591
0M
0)
1*
16
#593
1M
1)
#594
0*
06
#597
0M
0)
1*
16
#599
1M
1)
#600
0*
06
#603
0M
0)
1*
16
#605
1M
1)
#606
0*
06
#609
0M
0)
1*
16
#611
1M
1)
#612
0*
06
#615
0M
0)
1*
16
#617
1M
1)
#618
0*
06
#621
0M
0)
1*
16
#623
1M
1)
#624
0*
06
#627
0M
0)
1*
16
#629
1M
1)
#630
0*
06
#633
0M
0)
1*
16
#635
1M
1)
#636
0*
06
#639
0M
0)
1*
16
#641
1M
1)
#642
0*
06
#645
0M
0)
1*
16
#647
1M
1)
#648
0*
06
#651
0M
0)
1*
16
