Code/execute.v
/*
	Module written by Rahul Kejriwal
	CS14B023

	Synchronous module for execution and result storage 
*/

module executeAndStoreBack(
		input clk,
		input rst,

		input[ 3:0] opcode,
		input[ 3:0] destReg,
		input[15:0] srcVal1,
		input[15:0] srcVal2,
		input[ 7:0] memAddr, 
		input used1,
		input used2,

		output[ 3:0] destRegStore,
		output[15:0] destVal,
		output storeNow,
		input storeDone,

		output[ 7:0] memAddrLoadStore,
		output[15:0] memValueStore,

		input[15:0] memValueLoad,
		input valueReady,
		output readReq,

		output[15:0] ProcessorStatusWord,
	
		output powerdown
	);

	reg[ 3:0] destRegStore;
	reg[ 7:0] memAddrLoadStore;
	reg[15:0] destVal, memValueStore;

	reg[15:0] LastComputedValue;
	reg[15:0] ProcessorStatusWord;

	reg readReq, storeNow;
	reg[15:0] val1, val2;
	reg powerdown;

	initial begin
		destRegStore 		= 4'b0;
		memAddrLoadStore	= 8'b0;
		memValueStore		= 16'b0;
		destVal				= 16'b0;
		
		LastComputedValue   = 16'b0;
		ProcessorStatusWord = 16'b0;		
		
		readReq = 0;
		storeNow = 0;
		val1 = 16'b0;
		val2 = 16'b0;
		powerdown = 0;
	end

	always @(posedge rst) begin
		destRegStore 		= 4'b0;
		memAddrLoadStore	= 8'b0;
		memValueStore		= 16'b0;
		destVal				= 16'b0;
		
		LastComputedValue   = 16'b0;
		ProcessorStatusWord = 16'b0;
		
		readReq = 0;
		storeNow = 0;
		val1 = 16'b0;
		val2 = 16'b0;
	end

	always @(posedge clk) begin
		ProcessorStatusWord = 16'b0;
		
		// Write Sync Signal for register writes
		storeNow = 0;

		// Checking if src1 was being computed
		if(used1)
			val1 = LastComputedValue;
		else
			val1 = srcVal1;			

		// Checking if src2 was being computed
		if(used2)
			val2 = LastComputedValue;
		else
			val2 = srcVal2;			

		// Execute appropriate action for the opcode
		case(opcode)
			// NOP
			 0: begin
			 		// Doing nothing
			 	end 

			// HLT
			 1: begin
			 		powerdown = 1;
			 	end

			// ADD
			 2: begin
				 	{ProcessorStatusWord[15],destVal} = val1 + val2;
				 	
				 	if(val1[15] == val2[15] && destVal[15] != val1[15])
				 		ProcessorStatusWord[14] = 1;
			 	end

			// SUB
			 3: begin
				 	{ProcessorStatusWord[15],destVal} = val1 - val2;
				 	
				 	if(val1[15] != val2[15] && destVal[15] != val1[15])
				 		ProcessorStatusWord[14] = 1;
			 	end 
			 
			// MUL
			 4: begin
				 	{ProcessorStatusWord[15],destVal} = val1 * val2;
				 	
					// To do: Detect overflow/underflow			 	
			 	end

			// SL
			 5: begin
				 	{ProcessorStatusWord[15],destVal} = val1 << val2;		 	
			 	end

			 
			// SR
			 6: begin
			 		{ProcessorStatusWord[15],destVal} = val1 >> val2;
			 	end
			 
			// AND
			 7: begin
			 		destVal = val1 & val2;
			 	end

			// OR
			 8: begin
			 		destVal = val1 | val2;
			 	end
			 
			// NOT
			 9: begin
			 		// ignores val2
				 	destVal = ~val1;
				end
			
			// XOR
			10: begin
					destVal = val1 ^ val2;
				end

			// LOAD
			14: begin
					memAddrLoadStore = memAddr;
					readReq = 1'b0;
				end

			// STORE
			15: begin
					memAddrLoadStore = memAddr;
					memValueStore = val1;
				end

			default:begin
					$display("Failure in execute unit!");
					powerdown = 1;
					end
		endcase

		// Set register address to write to and send signal to write to reg file
		if(opcode >= 2 && opcode <= 10) begin
			destRegStore = destReg;
			storeNow = 1;

		 	if(destVal == 0)
				ProcessorStatusWord[13] = 1;	
		end
	end

	// Sent signal to read mem location. Waiting for signal that value is ready.
	always @(posedge valueReady) begin
		readReq = 1'b0;
		destVal = memValueLoad;
		if(destVal == 0)
			ProcessorStatusWord[13] = 1;			
	end

endmodule

Testbench/execute_testbench.v
/*
	Module written by Debanjan Ghatak
	CS16S023

	Execution unit test bench
*/

`include "/home/debanjan/Desktop/DDV_pro/3-Stage-Pipeline/Code/execute.v"

module execute_TestBench(
		output clk,
		output rst,

		output[ 3:0] opcode,
		output[ 3:0] destReg,
		output[15:0] srcVal1,
		output[15:0] srcVal2,
		output[ 7:0] memAddr, 
		output used1,
		output used2,

		input[ 3:0] destRegStore,
		input[15:0] destVal,
		input storeNow,
		output storeDone,

		input[ 7:0] memAddrLoadStore,
		input[15:0] memValueStore,

		output[15:0] memValueLoad,
		output valueReady,
		input readReq,

		input[15:0] ProcessorStatusWord,
	
		input powerdown
	);

	reg clk, rst;
	reg[ 3:0] opcode;
 	reg[ 3:0] destReg;
	reg[15:0] srcVal1;
	reg[15:0] srcVal2;
	reg[ 7:0] memAddr;
	reg used1;
	reg used2, storeDone, valueReady;
	reg[15:0] memValueLoad;

	executeAndStoreBack E(clk, rst, opcode, destReg, srcVal1, srcVal2, memAddr, used1, used2, destRegStore, destVal, storeNow, storeDone, memAddrLoadStore, memValueStore, memValueLoad, valueReady, readReq, ProcessorStatusWord, powerdown);

	always begin
		#1 clk = ~clk;
	end

	initial begin
		$dumpfile("execute.vcd");
    	$dumpvars(0,execute_TestBench);

	clk=0;
	rst=0;

	$monitor($time,, "clk: %b, opcode: %b, destReg: %b, srcVal1: %b ,srcVal2: %b,memAddr: %b,used1: %b,used2:,destRegStore: %b,destVal: %b,storeNow: %b,storeDone: %b,memAddrLoadStore: %b,memValueStore: %b,memValueLoad: %b,valueReady: %b,readReq: %b,ProcessorStatusWord: %b,powerdown: %b", clk, opcode, destReg, srcVal1, srcVal2, memAddr, used1, used2, destRegStore, destVal, storeNow, storeDone, memAddrLoadStore, memValueStore, memValueLoad, valueReady, readReq, ProcessorStatusWord, powerdown);

        #5
	opcode=2;
	srcVal1=24;
	srcVal2=30;
	destReg=12;
	used1=0;
	used2=0;
	
	#6
	opcode=3;
	srcVal1=25;
	srcVal2=9;
	destReg=13;
	used1=0;
	used2=0;

	#6
	opcode=5;
	srcVal1=24;
	srcVal2=5;
	destReg=11;
	used1=0;
	used2=0;

	#6
	opcode=7;
	srcVal1=56;
	srcVal2=32;
	destReg=5;
	used1=0;
	used2=0;

	#6
	opcode=9;
	srcVal1=11;
	destReg=14;
	used1=0;
	used2=0;

	#6
	opcode=15;
	memAddr=180;
	srcVal1=45;
	used1=0;
	used2=0;

	#6
	opcode=2;
	srcVal1=15;
	srcVal2=14;
	destReg=2;
	used1=1;
	used2=1;

	#550 $finish;
       end
		
endmodule

Testbench/execute.vcd
$date
	Thu Feb 16 02:15:42 2017
$end
$version
	Icarus Verilog
$end
$timescale
	1s
$end
$scope module execute_TestBench $end
$var wire 16 ! ProcessorStatusWord [15:0] $end
$var wire 4 " destRegStore [3:0] $end
$var wire 16 # destVal [15:0] $end
$var wire 8 $ memAddrLoadStore [7:0] $end
$var wire 16 % memValueStore [15:0] $end
$var wire 1 & powerdown $end
$var wire 1 ' readReq $end
$var wire 1 ( storeNow $end
$var reg 1 ) clk $end
$var reg 4 * destReg [3:0] $end
$var reg 8 + memAddr [7:0] $end
$var reg 16 , memValueLoad [15:0] $end
$var reg 4 - opcode [3:0] $end
$var reg 1 . rst $end
$var reg 16 / srcVal1 [15:0] $end
$var reg 16 0 srcVal2 [15:0] $end
$var reg 1 1 storeDone $end
$var reg 1 2 used1 $end
$var reg 1 3 used2 $end
$var reg 1 4 valueReady $end
$scope module E $end
$var wire 1 5 clk $end
$var wire 4 6 destReg [3:0] $end
$var wire 8 7 memAddr [7:0] $end
$var wire 16 8 memValueLoad [15:0] $end
$var wire 4 9 opcode [3:0] $end
$var wire 1 : rst $end
$var wire 16 ; srcVal1 [15:0] $end
$var wire 16 < srcVal2 [15:0] $end
$var wire 1 = storeDone $end
$var wire 1 > used1 $end
$var wire 1 ? used2 $end
$var wire 1 @ valueReady $end
$var reg 16 A LastComputedValue [15:0] $end
$var reg 16 B ProcessorStatusWord [15:0] $end
$var reg 4 C destRegStore [3:0] $end
$var reg 16 D destVal [15:0] $end
$var reg 8 E memAddrLoadStore [7:0] $end
$var reg 16 F memValueStore [15:0] $end
$var reg 1 G powerdown $end
$var reg 1 H readReq $end
$var reg 1 I storeNow $end
$var reg 16 J val1 [15:0] $end
$var reg 16 K val2 [15:0] $end
$upscope $end
$upscope $end
$enddefinitions $end
#0
$dumpvars
b0 K
b0 J
0I
0H
0G
b0 F
b0 E
b0 D
b0 C
b0 B
b0 A
x@
x?
x>
x=
bx <
bx ;
0:
bx 9
bx 8
bx 7
bx 6
05
x4
x3
x2
x1
bx 0
bx /
0.
bx -
bx ,
bx +
bx *
0)
0(
0'
0&
b0 %
b0 $
b0 #
b0 "
b0 !
$end
#1
1G
1&
bx K
bx J
1)
15
#2
0)
05
#3
1)
15
#4
0)
05
#5
1I
1(
b1100 C
b1100 "
b0 B
b110110 D
b110110 #
b11110 K
b11000 J
1)
15
03
0?
02
0>
b1100 *
b1100 6
b11110 0
b11110 <
b11000 /
b11000 ;
b10 -
b10 9
#6
0)
05
#7
b0 B
1I
1(
1)
15
#8
0)
05
#9
b0 B
1I
1(
1)
15
#10
0)
05
#11
b1101 C
b1101 "
b0 B
b10000 D
b10000 #
b1001 K
b11001 J
1I
1(
1)
15
b1101 *
b1101 6
b1001 0
b1001 <
b11001 /
b11001 ;
b11 -
b11 9
#12
0)
05
#13
b0 B
1I
1(
1)
15
#14
0)
05
#15
b0 B
1I
1(
1)
15
#16
0)
05
#17
b1011 C
b1011 "
b0 B
b1100000000 D
b1100000000 #
b101 K
b11000 J
1I
1(
1)
15
b1011 *
b1011 6
b101 0
b101 <
b11000 /
b11000 ;
b101 -
b101 9
#18
0)
05
#19
b0 B
1I
1(
1)
15
#20
0)
05
#21
b0 B
1I
1(
1)
15
#22
0)
05
#23
b101 C
b101 "
b100000 D
b100000 #
b100000 K
b111000 J
1I
1(
1)
15
b101 *
b101 6
b100000 0
b100000 <
b111000 /
b111000 ;
b111 -
b111 9
#24
0)
05
#25
1I
1(
1)
15
#26
0)
05
#27
1I
1(
1)
15
#28
0)
05
#29
b1110 C
b1110 "
b1111111111110100 D
b1111111111110100 #
b1011 J
1I
1(
1)
15
b1110 *
b1110 6
b1011 /
b1011 ;
b1001 -
b1001 9
#30
0)
05
#31
1I
1(
1)
15
#32
0)
05
#33
1I
1(
1)
15
#34
0)
05
#35
b101101 F
b101101 %
b10110100 E
b10110100 $
b101101 J
0I
0(
1)
15
b101101 /
b101101 ;
b10110100 +
b10110100 7
b1111 -
b1111 9
#36
0)
05
#37
1)
15
#38
0)
05
#39
1)
15
#40
0)
05
#41
b10000000000000 !
1I
1(
b10 C
b10 "
b10000000000000 B
b0 D
b0 #
b0 K
b0 J
1)
15
13
1?
12
1>
b10 *
b10 6
b1110 0
b1110 <
b1111 /
b1111 ;
b10 -
b10 9
#42
0)
05
#43
1I
1(
b10000000000000 B
b10000000000000 !
1)
15
#44
0)
05
#45
1I
1(
b10000000000000 B
b10000000000000 !
1)
15
#46
0)
05
#47
1I
1(
b10000000000000 B
b10000000000000 !
1)
15
#48
0)
05
#49
1I
1(
b10000000000000 B
b10000000000000 !
1)
15
#50
0)
05
#51
1I
1(
b10000000000000 B
b10000000000000 !
1)
15
#52
0)
05
#53
1I
1(
b10000000000000 B
b10000000000000 !
1)
15
#54
0)
05
#55
1I
1(
b10000000000000 B
b10000000000000 !
1)
15
#56
0)
05
#57
1I
1(
b10000000000000 B
b10000000000000 !
1)
15
#58
0)
05
#59
1I
1(
b10000000000000 B
b10000000000000 !
1)
15
#60
0)
05
#61
1I
1(
b10000000000000 B
b10000000000000 !
1)
15
#62
0)
05
#63
1I
1(
b10000000000000 B
b10000000000000 !
1)
15
#64
0)
05
#65
1I
1(
b10000000000000 B
b10000000000000 !
1)
15
#66
0)
05
#67
1I
1(
b10000000000000 B
b10000000000000 !
1)
15
#68
0)
05
#69
1I
1(
b10000000000000 B
b10000000000000 !
1)
15
#70
0)
05
#71
1I
1(
b10000000000000 B
b10000000000000 !
1)
15
#72
0)
05
#73
1I
1(
b10000000000000 B
b10000000000000 !
1)
15
#74
0)
05
#75
1I
1(
b10000000000000 B
b10000000000000 !
1)
15
#76
0)
05
#77
1I
1(
b10000000000000 B
b10000000000000 !
1)
15
#78
0)
05
#79
1I
1(
b10000000000000 B
b10000000000000 !
1)
15
#80
0)
05
#81
1I
1(
b10000000000000 B
b10000000000000 !
1)
15
#82
0)
05
#83
1I
1(
b10000000000000 B
b10000000000000 !
1)
15
#84
0)
05
#85
1I
1(
b10000000000000 B
b10000000000000 !
1)
15
#86
0)
05
#87
1I
1(
b10000000000000 B
b10000000000000 !
1)
15
#88
0)
05
#89
1I
1(
b10000000000000 B
b10000000000000 !
1)
15
#90
0)
05
#91
1I
1(
b10000000000000 B
b10000000000000 !
1)
15
#92
0)
05
#93
1I
1(
b10000000000000 B
b10000000000000 !
1)
15
#94
0)
05
#95
1I
1(
b10000000000000 B
b10000000000000 !
1)
15
#96
0)
05
#97
1I
1(
b10000000000000 B
b10000000000000 !
1)
15
#98
0)
05
#99
1I
1(
b10000000000000 B
b10000000000000 !
1)
15
#100
0)
05
#101
1I
1(
b10000000000000 B
b10000000000000 !
1)
15
#102
0)
05
#103
1I
1(
b10000000000000 B
b10000000000000 !
1)
15
#104
0)
05
#105
1I
1(
b10000000000000 B
b10000000000000 !
1)
15
#106
0)
05
#107
1I
1(
b10000000000000 B
b10000000000000 !
1)
15
#108
0)
05
#109
1I
1(
b10000000000000 B
b10000000000000 !
1)
15
#110
0)
05
#111
1I
1(
b10000000000000 B
b10000000000000 !
1)
15
#112
0)
05
#113
1I
1(
b10000000000000 B
b10000000000000 !
1)
15
#114
0)
05
#115
1I
1(
b10000000000000 B
b10000000000000 !
1)
15
#116
0)
05
#117
1I
1(
b10000000000000 B
b10000000000000 !
1)
15
#118
0)
05
#119
1I
1(
b10000000000000 B
b10000000000000 !
1)
15
#120
0)
05
#121
1I
1(
b10000000000000 B
b10000000000000 !
1)
15
#122
0)
05
#123
1I
1(
b10000000000000 B
b10000000000000 !
1)
15
#124
0)
05
#125
1I
1(
b10000000000000 B
b10000000000000 !
1)
15
#126
0)
05
#127
1I
1(
b10000000000000 B
b10000000000000 !
1)
15
#128
0)
05
#129
1I
1(
b10000000000000 B
b10000000000000 !
1)
15
#130
0)
05
#131
1I
1(
b10000000000000 B
b10000000000000 !
1)
15
#132
0)
05
#133
1I
1(
b10000000000000 B
b10000000000000 !
1)
15
#134
0)
05
#135
1I
1(
b10000000000000 B
b10000000000000 !
1)
15
#136
0)
05
#137
1I
1(
b10000000000000 B
b10000000000000 !
1)
15
#138
0)
05
#139
1I
1(
b10000000000000 B
b10000000000000 !
1)
15
#140
0)
05
#141
1I
1(
b10000000000000 B
b10000000000000 !
1)
15
#142
0)
05
#143
1I
1(
b10000000000000 B
b10000000000000 !
1)
15
#144
0)
05
#145
1I
1(
b10000000000000 B
b10000000000000 !
1)
15
#146
0)
05
#147
1I
1(
b10000000000000 B
b10000000000000 !
1)
15
#148
0)
05
#149
1I
1(
b10000000000000 B
b10000000000000 !
1)
15
#150
0)
05
#151
1I
1(
b10000000000000 B
b10000000000000 !
1)
15
#152
0)
05
#153
1I
1(
b10000000000000 B
b10000000000000 !
1)
15
#154
0)
05
#155
1I
1(
b10000000000000 B
b10000000000000 !
1)
15
#156
0)
05
#157
1I
1(
b10000000000000 B
b10000000000000 !
1)
15
#158
0)
05
#159
1I
1(
b10000000000000 B
b10000000000000 !
1)
15
#160
0)
05
#161
1I
1(
b10000000000000 B
b10000000000000 !
1)
15
#162
0)
05
#163
1I
1(
b10000000000000 B
b10000000000000 !
1)
15
#164
0)
05
#165
1I
1(
b10000000000000 B
b10000000000000 !
1)
15
#166
0)
05
#167
1I
1(
b10000000000000 B
b10000000000000 !
1)
15
#168
0)
05
#169
1I
1(
b10000000000000 B
b10000000000000 !
1)
15
#170
0)
05
#171
1I
1(
b10000000000000 B
b10000000000000 !
1)
15
#172
0)
05
#173
1I
1(
b10000000000000 B
b10000000000000 !
1)
15
#174
0)
05
#175
1I
1(
b10000000000000 B
b10000000000000 !
1)
15
#176
0)
05
#177
1I
1(
b10000000000000 B
b10000000000000 !
1)
15
#178
0)
05
#179
1I
1(
b10000000000000 B
b10000000000000 !
1)
15
#180
0)
05
#181
1I
1(
b10000000000000 B
b10000000000000 !
1)
15
#182
0)
05
#183
1I
1(
b10000000000000 B
b10000000000000 !
1)
15
#184
0)
05
#185
1I
1(
b10000000000000 B
b10000000000000 !
1)
15
#186
0)
05
#187
1I
1(
b10000000000000 B
b10000000000000 !
1)
15
#188
0)
05
#189
1I
1(
b10000000000000 B
b10000000000000 !
1)
15
#190
0)
05
#191
1I
1(
b10000000000000 B
b10000000000000 !
1)
15
#192
0)
05
#193
1I
1(
b10000000000000 B
b10000000000000 !
1)
15
#194
0)
05
#195
1I
1(
b10000000000000 B
b10000000000000 !
1)
15
#196
0)
05
#197
1I
1(
b10000000000000 B
b10000000000000 !
1)
15
#198
0)
05
#199
1I
1(
b10000000000000 B
b10000000000000 !
1)
15
#200
0)
05
#201
1I
1(
b10000000000000 B
b10000000000000 !
1)
15
#202
0)
05
#203
1I
1(
b10000000000000 B
b10000000000000 !
1)
15
#204
0)
05
#205
1I
1(
b10000000000000 B
b10000000000000 !
1)
15
#206
0)
05
#207
1I
1(
b10000000000000 B
b10000000000000 !
1)
15
#208
0)
05
#209
1I
1(
b10000000000000 B
b10000000000000 !
1)
15
#210
0)
05
#211
1I
1(
b10000000000000 B
b10000000000000 !
1)
15
#212
0)
05
#213
1I
1(
b10000000000000 B
b10000000000000 !
1)
15
#214
0)
05
#215
1I
1(
b10000000000000 B
b10000000000000 !
1)
15
#216
0)
05
#217
1I
1(
b10000000000000 B
b10000000000000 !
1)
15
#218
0)
05
#219
1I
1(
b10000000000000 B
b10000000000000 !
1)
15
#220
0)
05
#221
1I
1(
b10000000000000 B
b10000000000000 !
1)
15
#222
0)
05
#223
1I
1(
b10000000000000 B
b10000000000000 !
1)
15
#224
0)
05
#225
1I
1(
b10000000000000 B
b10000000000000 !
1)
15
#226
0)
05
#227
1I
1(
b10000000000000 B
b10000000000000 !
1)
15
#228
0)
05
#229
1I
1(
b10000000000000 B
b10000000000000 !
1)
15
#230
0)
05
#231
1I
1(
b10000000000000 B
b10000000000000 !
1)
15
#232
0)
05
#233
1I
1(
b10000000000000 B
b10000000000000 !
1)
15
#234
0)
05
#235
1I
1(
b10000000000000 B
b10000000000000 !
1)
15
#236
0)
05
#237
1I
1(
b10000000000000 B
b10000000000000 !
1)
15
#238
0)
05
#239
1I
1(
b10000000000000 B
b10000000000000 !
1)
15
#240
0)
05
#241
1I
1(
b10000000000000 B
b10000000000000 !
1)
15
#242
0)
05
#243
1I
1(
b10000000000000 B
b10000000000000 !
1)
15
#244
0)
05
#245
1I
1(
b10000000000000 B
b10000000000000 !
1)
15
#246
0)
05
#247
1I
1(
b10000000000000 B
b10000000000000 !
1)
15
#248
0)
05
#249
1I
1(
b10000000000000 B
b10000000000000 !
1)
15
#250
0)
05
#251
1I
1(
b10000000000000 B
b10000000000000 !
1)
15
#252
0)
05
#253
1I
1(
b10000000000000 B
b10000000000000 !
1)
15
#254
0)
05
#255
1I
1(
b10000000000000 B
b10000000000000 !
1)
15
#256
0)
05
#257
1I
1(
b10000000000000 B
b10000000000000 !
1)
15
#258
0)
05
#259
1I
1(
b10000000000000 B
b10000000000000 !
1)
15
#260
0)
05
#261
1I
1(
b10000000000000 B
b10000000000000 !
1)
15
#262
0)
05
#263
1I
1(
b10000000000000 B
b10000000000000 !
1)
15
#264
0)
05
#265
1I
1(
b10000000000000 B
b10000000000000 !
1)
15
#266
0)
05
#267
1I
1(
b10000000000000 B
b10000000000000 !
1)
15
#268
0)
05
#269
1I
1(
b10000000000000 B
b10000000000000 !
1)
15
#270
0)
05
#271
1I
1(
b10000000000000 B
b10000000000000 !
1)
15
#272
0)
05
#273
1I
1(
b10000000000000 B
b10000000000000 !
1)
15
#274
0)
05
#275
1I
1(
b10000000000000 B
b10000000000000 !
1)
15
#276
0)
05
#277
1I
1(
b10000000000000 B
b10000000000000 !
1)
15
#278
0)
05
#279
1I
1(
b10000000000000 B
b10000000000000 !
1)
15
#280
0)
05
#281
1I
1(
b10000000000000 B
b10000000000000 !
1)
15
#282
0)
05
#283
1I
1(
b10000000000000 B
b10000000000000 !
1)
15
#284
0)
05
#285
1I
1(
b10000000000000 B
b10000000000000 !
1)
15
#286
0)
05
#287
1I
1(
b10000000000000 B
b10000000000000 !
1)
15
#288
0)
05
#289
1I
1(
b10000000000000 B
b10000000000000 !
1)
15
#290
0)
05
#291
1I
1(
b10000000000000 B
b10000000000000 !
1)
15
#292
0)
05
#293
1I
1(
b10000000000000 B
b10000000000000 !
1)
15
#294
0)
05
#295
1I
1(
b10000000000000 B
b10000000000000 !
1)
15
#296
0)
05
#297
1I
1(
b10000000000000 B
b10000000000000 !
1)
15
#298
0)
05
#299
1I
1(
b10000000000000 B
b10000000000000 !
1)
15
#300
0)
05
#301
1I
1(
b10000000000000 B
b10000000000000 !
1)
15
#302
0)
05
#303
1I
1(
b10000000000000 B
b10000000000000 !
1)
15
#304
0)
05
#305
1I
1(
b10000000000000 B
b10000000000000 !
1)
15
#306
0)
05
#307
1I
1(
b10000000000000 B
b10000000000000 !
1)
15
#308
0)
05
#309
1I
1(
b10000000000000 B
b10000000000000 !
1)
15
#310
0)
05
#311
1I
1(
b10000000000000 B
b10000000000000 !
1)
15
#312
0)
05
#313
1I
1(
b10000000000000 B
b10000000000000 !
1)
15
#314
0)
05
#315
1I
1(
b10000000000000 B
b10000000000000 !
1)
15
#316
0)
05
#317
1I
1(
b10000000000000 B
b10000000000000 !
1)
15
#318
0)
05
#319
1I
1(
b10000000000000 B
b10000000000000 !
1)
15
#320
0)
05
#321
1I
1(
b10000000000000 B
b10000000000000 !
1)
15
#322
0)
05
#323
1I
1(
b10000000000000 B
b10000000000000 !
1)
15
#324
0)
05
#325
1I
1(
b10000000000000 B
b10000000000000 !
1)
15
#326
0)
05
#327
1I
1(
b10000000000000 B
b10000000000000 !
1)
15
#328
0)
05
#329
1I
1(
b10000000000000 B
b10000000000000 !
1)
15
#330
0)
05
#331
1I
1(
b10000000000000 B
b10000000000000 !
1)
15
#332
0)
05
#333
1I
1(
b10000000000000 B
b10000000000000 !
1)
15
#334
0)
05
#335
1I
1(
b10000000000000 B
b10000000000000 !
1)
15
#336
0)
05
#337
1I
1(
b10000000000000 B
b10000000000000 !
1)
15
#338
0)
05
#339
1I
1(
b10000000000000 B
b10000000000000 !
1)
15
#340
0)
05
#341
1I
1(
b10000000000000 B
b10000000000000 !
1)
15
#342
0)
05
#343
1I
1(
b10000000000000 B
b10000000000000 !
1)
15
#344
0)
05
#345
1I
1(
b10000000000000 B
b10000000000000 !
1)
15
#346
0)
05
#347
1I
1(
b10000000000000 B
b10000000000000 !
1)
15
#348
0)
05
#349
1I
1(
b10000000000000 B
b10000000000000 !
1)
15
#350
0)
05
#351
1I
1(
b10000000000000 B
b10000000000000 !
1)
15
#352
0)
05
#353
1I
1(
b10000000000000 B
b10000000000000 !
1)
15
#354
0)
05
#355
1I
1(
b10000000000000 B
b10000000000000 !
1)
15
#356
0)
05
#357
1I
1(
b10000000000000 B
b10000000000000 !
1)
15
#358
0)
05
#359
1I
1(
b10000000000000 B
b10000000000000 !
1)
15
#360
0)
05
#361
1I
1(
b10000000000000 B
b10000000000000 !
1)
15
#362
0)
05
#363
1I
1(
b10000000000000 B
b10000000000000 !
1)
15
#364
0)
05
#365
1I
1(
b10000000000000 B
b10000000000000 !
1)
15
#366
0)
05
#367
1I
1(
b10000000000000 B
b10000000000000 !
1)
15
#368
0)
05
#369
1I
1(
b10000000000000 B
b10000000000000 !
1)
15
#370
0)
05
#371
1I
1(
b10000000000000 B
b10000000000000 !
1)
15
#372
0)
05
#373
1I
1(
b10000000000000 B
b10000000000000 !
1)
15
#374
0)
05
#375
1I
1(
b10000000000000 B
b10000000000000 !
1)
15
#376
0)
05
#377
1I
1(
b10000000000000 B
b10000000000000 !
1)
15
#378
0)
05
#379
1I
1(
b10000000000000 B
b10000000000000 !
1)
15
#380
0)
05
#381
1I
1(
b10000000000000 B
b10000000000000 !
1)
15
#382
0)
05
#383
1I
1(
b10000000000000 B
b10000000000000 !
1)
15
#384
0)
05
#385
1I
1(
b10000000000000 B
b10000000000000 !
1)
15
#386
0)
05
#387
1I
1(
b10000000000000 B
b10000000000000 !
1)
15
#388
0)
05
#389
1I
1(
b10000000000000 B
b10000000000000 !
1)
15
#390
0)
05
#391
1I
1(
b10000000000000 B
b10000000000000 !
1)
15
#392
0)
05
#393
1I
1(
b10000000000000 B
b10000000000000 !
1)
15
#394
0)
05
#395
1I
1(
b10000000000000 B
b10000000000000 !
1)
15
#396
0)
05
#397
1I
1(
b10000000000000 B
b10000000000000 !
1)
15
#398
0)
05
#399
1I
1(
b10000000000000 B
b10000000000000 !
1)
15
#400
0)
05
#401
1I
1(
b10000000000000 B
b10000000000000 !
1)
15
#402
0)
05
#403
1I
1(
b10000000000000 B
b10000000000000 !
1)
15
#404
0)
05
#405
1I
1(
b10000000000000 B
b10000000000000 !
1)
15
#406
0)
05
#407
1I
1(
b10000000000000 B
b10000000000000 !
1)
15
#408
0)
05
#409
1I
1(
b10000000000000 B
b10000000000000 !
1)
15
#410
0)
05
#411
1I
1(
b10000000000000 B
b10000000000000 !
1)
15
#412
0)
05
#413
1I
1(
b10000000000000 B
b10000000000000 !
1)
15
#414
0)
05
#415
1I
1(
b10000000000000 B
b10000000000000 !
1)
15
#416
0)
05
#417
1I
1(
b10000000000000 B
b10000000000000 !
1)
15
#418
0)
05
#419
1I
1(
b10000000000000 B
b10000000000000 !
1)
15
#420
0)
05
#421
1I
1(
b10000000000000 B
b10000000000000 !
1)
15
#422
0)
05
#423
1I
1(
b10000000000000 B
b10000000000000 !
1)
15
#424
0)
05
#425
1I
1(
b10000000000000 B
b10000000000000 !
1)
15
#426
0)
05
#427
1I
1(
b10000000000000 B
b10000000000000 !
1)
15
#428
0)
05
#429
1I
1(
b10000000000000 B
b10000000000000 !
1)
15
#430
0)
05
#431
1I
1(
b10000000000000 B
b10000000000000 !
1)
15
#432
0)
05
#433
1I
1(
b10000000000000 B
b10000000000000 !
1)
15
#434
0)
05
#435
1I
1(
b10000000000000 B
b10000000000000 !
1)
15
#436
0)
05
#437
1I
1(
b10000000000000 B
b10000000000000 !
1)
15
#438
0)
05
#439
1I
1(
b10000000000000 B
b10000000000000 !
1)
15
#440
0)
05
#441
1I
1(
b10000000000000 B
b10000000000000 !
1)
15
#442
0)
05
#443
1I
1(
b10000000000000 B
b10000000000000 !
1)
15
#444
0)
05
#445
1I
1(
b10000000000000 B
b10000000000000 !
1)
15
#446
0)
05
#447
1I
1(
b10000000000000 B
b10000000000000 !
1)
15
#448
0)
05
#449
1I
1(
b10000000000000 B
b10000000000000 !
1)
15
#450
0)
05
#451
1I
1(
b10000000000000 B
b10000000000000 !
1)
15
#452
0)
05
#453
1I
1(
b10000000000000 B
b10000000000000 !
1)
15
#454
0)
05
#455
1I
1(
b10000000000000 B
b10000000000000 !
1)
15
#456
0)
05
#457
1I
1(
b10000000000000 B
b10000000000000 !
1)
15
#458
0)
05
#459
1I
1(
b10000000000000 B
b10000000000000 !
1)
15
#460
0)
05
#461
1I
1(
b10000000000000 B
b10000000000000 !
1)
15
#462
0)
05
#463
1I
1(
b10000000000000 B
b10000000000000 !
1)
15
#464
0)
05
#465
1I
1(
b10000000000000 B
b10000000000000 !
1)
15
#466
0)
05
#467
1I
1(
b10000000000000 B
b10000000000000 !
1)
15
#468
0)
05
#469
1I
1(
b10000000000000 B
b10000000000000 !
1)
15
#470
0)
05
#471
1I
1(
b10000000000000 B
b10000000000000 !
1)
15
#472
0)
05
#473
1I
1(
b10000000000000 B
b10000000000000 !
1)
15
#474
0)
05
#475
1I
1(
b10000000000000 B
b10000000000000 !
1)
15
#476
0)
05
#477
1I
1(
b10000000000000 B
b10000000000000 !
1)
15
#478
0)
05
#479
1I
1(
b10000000000000 B
b10000000000000 !
1)
15
#480
0)
05
#481
1I
1(
b10000000000000 B
b10000000000000 !
1)
15
#482
0)
05
#483
1I
1(
b10000000000000 B
b10000000000000 !
1)
15
#484
0)
05
#485
1I
1(
b10000000000000 B
b10000000000000 !
1)
15
#486
0)
05
#487
1I
1(
b10000000000000 B
b10000000000000 !
1)
15
#488
0)
05
#489
1I
1(
b10000000000000 B
b10000000000000 !
1)
15
#490
0)
05
#491
1I
1(
b10000000000000 B
b10000000000000 !
1)
15
#492
0)
05
#493
1I
1(
b10000000000000 B
b10000000000000 !
1)
15
#494
0)
05
#495
1I
1(
b10000000000000 B
b10000000000000 !
1)
15
#496
0)
05
#497
1I
1(
b10000000000000 B
b10000000000000 !
1)
15
#498
0)
05
#499
1I
1(
b10000000000000 B
b10000000000000 !
1)
15
#500
0)
05
#501
1I
1(
b10000000000000 B
b10000000000000 !
1)
15
#502
0)
05
#503
1I
1(
b10000000000000 B
b10000000000000 !
1)
15
#504
0)
05
#505
1I
1(
b10000000000000 B
b10000000000000 !
1)
15
#506
0)
05
#507
1I
1(
b10000000000000 B
b10000000000000 !
1)
15
#508
0)
05
#509
1I
1(
b10000000000000 B
b10000000000000 !
1)
15
#510
0)
05
#511
1I
1(
b10000000000000 B
b10000000000000 !
1)
15
#512
0)
05
#513
1I
1(
b10000000000000 B
b10000000000000 !
1)
15
#514
0)
05
#515
1I
1(
b10000000000000 B
b10000000000000 !
1)
15
#516
0)
05
#517
1I
1(
b10000000000000 B
b10000000000000 !
1)
15
#518
0)
05
#519
1I
1(
b10000000000000 B
b10000000000000 !
1)
15
#520
0)
05
#521
1I
1(
b10000000000000 B
b10000000000000 !
1)
15
#522
0)
05
#523
1I
1(
b10000000000000 B
b10000000000000 !
1)
15
