Code/fetch.v
/*
	Module written by Rahul Kejriwal
	CS14B023

	Synchronous module to fetch instructions
*/

module fetchInstruction(
		input clk,
		input rst,

		output[7:0] prog_ctr,
		input[15:0] instr,

		output[15:0] curr_instr
	);

	// Program Counter
	reg[ 7:0] prog_ctr;
	// Instruction Register
	reg[15:0] curr_instr;

	initial begin
 		prog_ctr	= 8'b0;
 		curr_instr	= 16'b0;		
	end

 	always @(posedge rst) begin
 		prog_ctr	= 8'b0;
 		curr_instr	= 16'b0;
 	end

 	always @(posedge clk) begin
	 	curr_instr = instr;
 		prog_ctr += 1;
 	end
endmodule

Testbench/fetch_testbench.v
/*
	Module written by Rahul Kejriwal
	CS14B023

	Fetch unit test bench
*/

`include "../Code/fetch.v"

module fetch_TestBench(
		output clk,
		output rst,

		input[7:0] instr_addr,
		output[15:0] instr,

		input[15:0] curr_instr
	);

	reg clk, rst;
	reg[15:0] instr;

	fetchInstruction I(clk, rst, instr_addr, instr, curr_instr);

	always begin
		#1 clk = ~clk;
	end

	initial begin
		$dumpfile("fetch.vcd");
    	$dumpvars(0,fetch_TestBench);

		clk = 0;
		rst = 0;
		instr = 0;
	
		$monitor($time,, "clk: %b, Address: %b, IR: %b, ISent: %b", clk, instr_addr, curr_instr, instr);
		#550 $finish;
	end

	always @(instr_addr) begin
		instr = instr_addr << 8 | instr_addr ^ 8'b11111111;
	end 
endmodule

Testbench/fetch.vcd
$date
	Fri Feb 10 23:52:19 2017
$end
$version
	Icarus Verilog
$end
$timescale
	1s
$end
$scope module fetch_TestBench $end
$var wire 8 ! instr_addr [7:0] $end
$var wire 16 " curr_instr [15:0] $end
$var reg 1 # clk $end
$var reg 16 $ instr [15:0] $end
$var reg 1 % rst $end
$scope module I $end
$var wire 1 # clk $end
$var wire 16 & instr [15:0] $end
$var wire 1 % rst $end
$var reg 16 ' curr_instr [15:0] $end
$var reg 8 ( prog_ctr [7:0] $end
$upscope $end
$upscope $end
$enddefinitions $end
#0
$dumpvars
b0 (
b0 '
b11111111 &
0%
b11111111 $
0#
b0 "
b0 !
$end
#1
b111111110 $
b111111110 &
b1 !
b1 (
b11111111 "
b11111111 '
1#
#2
0#
#3
b1011111101 $
b1011111101 &
b10 !
b10 (
b111111110 "
b111111110 '
1#
#4
0#
#5
b1111111100 $
b1111111100 &
b11 !
b11 (
b1011111101 "
b1011111101 '
1#
#6
0#
#7
b10011111011 $
b10011111011 &
b100 !
b100 (
b1111111100 "
b1111111100 '
1#
#8
0#
#9
b10111111010 $
b10111111010 &
b101 !
b101 (
b10011111011 "
b10011111011 '
1#
#10
0#
#11
b11011111001 $
b11011111001 &
b110 !
b110 (
b10111111010 "
b10111111010 '
1#
#12
0#
#13
b11111111000 $
b11111111000 &
b111 !
b111 (
b11011111001 "
b11011111001 '
1#
#14
0#
#15
b100011110111 $
b100011110111 &
b1000 !
b1000 (
b11111111000 "
b11111111000 '
1#
#16
0#
#17
b100111110110 $
b100111110110 &
b1001 !
b1001 (
b100011110111 "
b100011110111 '
1#
#18
0#
#19
b101011110101 $
b101011110101 &
b1010 !
b1010 (
b100111110110 "
b100111110110 '
1#
#20
0#
#21
b101111110100 $
b101111110100 &
b1011 !
b1011 (
b101011110101 "
b101011110101 '
1#
#22
0#
#23
b110011110011 $
b110011110011 &
b1100 !
b1100 (
b101111110100 "
b101111110100 '
1#
#24
0#
#25
b110111110010 $
b110111110010 &
b1101 !
b1101 (
b110011110011 "
b110011110011 '
1#
#26
0#
#27
b111011110001 $
b111011110001 &
b1110 !
b1110 (
b110111110010 "
b110111110010 '
1#
#28
0#
#29
b111111110000 $
b111111110000 &
b1111 !
b1111 (
b111011110001 "
b111011110001 '
1#
#30
0#
#31
b1000011101111 $
b1000011101111 &
b10000 !
b10000 (
b111111110000 "
b111111110000 '
1#
#32
0#
#33
b1000111101110 $
b1000111101110 &
b10001 !
b10001 (
b1000011101111 "
b1000011101111 '
1#
#34
0#
#35
b1001011101101 $
b1001011101101 &
b10010 !
b10010 (
b1000111101110 "
b1000111101110 '
1#
#36
0#
#37
b1001111101100 $
b1001111101100 &
b10011 !
b10011 (
b1001011101101 "
b1001011101101 '
1#
#38
0#
#39
b1010011101011 $
b1010011101011 &
b10100 !
b10100 (
b1001111101100 "
b1001111101100 '
1#
#40
0#
#41
b1010111101010 $
b1010111101010 &
b10101 !
b10101 (
b1010011101011 "
b1010011101011 '
1#
#42
0#
#43
b1011011101001 $
b1011011101001 &
b10110 !
b10110 (
b1010111101010 "
b1010111101010 '
1#
#44
0#
#45
b1011111101000 $
b1011111101000 &
b10111 !
b10111 (
b1011011101001 "
b1011011101001 '
1#
#46
0#
#47
b1100011100111 $
b1100011100111 &
b11000 !
b11000 (
b1011111101000 "
b1011111101000 '
1#
#48
0#
#49
b1100111100110 $
b1100111100110 &
b11001 !
b11001 (
b1100011100111 "
b1100011100111 '
1#
#50
0#
#51
b1101011100101 $
b1101011100101 &
b11010 !
b11010 (
b1100111100110 "
b1100111100110 '
1#
#52
0#
#53
b1101111100100 $
b1101111100100 &
b11011 !
b11011 (
b1101011100101 "
b1101011100101 '
1#
#54
0#
#55
b1110011100011 $
b1110011100011 &
b11100 !
b11100 (
b1101111100100 "
b1101111100100 '
1#
#56
0#
#57
b1110111100010 $
b1110111100010 &
b11101 !
b11101 (
b1110011100011 "
b1110011100011 '
1#
#58
0#
#59
b1111011100001 $
b1111011100001 &
b11110 !
b11110 (
b1110111100010 "
b1110111100010 '
1#
#60
0#
#61
b1111111100000 $
b1111111100000 &
b11111 !
b11111 (
b1111011100001 "
b1111011100001 '
1#
#62
0#
#63
b10000011011111 $
b10000011011111 &
b100000 !
b100000 (
b1111111100000 "
b1111111100000 '
1#
#64
0#
#65
b10000111011110 $
b10000111011110 &
b100001 !
b100001 (
b10000011011111 "
b10000011011111 '
1#
#66
0#
#67
b10001011011101 $
b10001011011101 &
b100010 !
b100010 (
b10000111011110 "
b10000111011110 '
1#
#68
0#
#69
b10001111011100 $
b10001111011100 &
b100011 !
b100011 (
b10001011011101 "
b10001011011101 '
1#
#70
0#
#71
b10010011011011 $
b10010011011011 &
b100100 !
b100100 (
b10001111011100 "
b10001111011100 '
1#
#72
0#
#73
b10010111011010 $
b10010111011010 &
b100101 !
b100101 (
b10010011011011 "
b10010011011011 '
1#
#74
0#
#75
b10011011011001 $
b10011011011001 &
b100110 !
b100110 (
b10010111011010 "
b10010111011010 '
1#
#76
0#
#77
b10011111011000 $
b10011111011000 &
b100111 !
b100111 (
b10011011011001 "
b10011011011001 '
1#
#78
0#
#79
b10100011010111 $
b10100011010111 &
b101000 !
b101000 (
b10011111011000 "
b10011111011000 '
1#
#80
0#
#81
b10100111010110 $
b10100111010110 &
b101001 !
b101001 (
b10100011010111 "
b10100011010111 '
1#
#82
0#
#83
b10101011010101 $
b10101011010101 &
b101010 !
b101010 (
b10100111010110 "
b10100111010110 '
1#
#84
0#
#85
b10101111010100 $
b10101111010100 &
b101011 !
b101011 (
b10101011010101 "
b10101011010101 '
1#
#86
0#
#87
b10110011010011 $
b10110011010011 &
b101100 !
b101100 (
b10101111010100 "
b10101111010100 '
1#
#88
0#
#89
b10110111010010 $
b10110111010010 &
b101101 !
b101101 (
b10110011010011 "
b10110011010011 '
1#
#90
0#
#91
b10111011010001 $
b10111011010001 &
b101110 !
b101110 (
b10110111010010 "
b10110111010010 '
1#
#92
0#
#93
b10111111010000 $
b10111111010000 &
b101111 !
b101111 (
b10111011010001 "
b10111011010001 '
1#
#94
0#
#95
b11000011001111 $
b11000011001111 &
b110000 !
b110000 (
b10111111010000 "
b10111111010000 '
1#
#96
0#
#97
b11000111001110 $
b11000111001110 &
b110001 !
b110001 (
b11000011001111 "
b11000011001111 '
1#
#98
0#
#99
b11001011001101 $
b11001011001101 &
b110010 !
b110010 (
b11000111001110 "
b11000111001110 '
1#
#100
0#
#101
b11001111001100 $
b11001111001100 &
b110011 !
b110011 (
b11001011001101 "
b11001011001101 '
1#
#102
0#
#103
b11010011001011 $
b11010011001011 &
b110100 !
b110100 (
b11001111001100 "
b11001111001100 '
1#
#104
0#
#105
b11010111001010 $
b11010111001010 &
b110101 !
b110101 (
b11010011001011 "
b11010011001011 '
1#
#106
0#
#107
b11011011001001 $
b11011011001001 &
b110110 !
b110110 (
b11010111001010 "
b11010111001010 '
1#
#108
0#
#109
b11011111001000 $
b11011111001000 &
b110111 !
b110111 (
b11011011001001 "
b11011011001001 '
1#
#110
0#
#111
b11100011000111 $
b11100011000111 &
b111000 !
b111000 (
b11011111001000 "
b11011111001000 '
1#
#112
0#
#113
b11100111000110 $
b11100111000110 &
b111001 !
b111001 (
b11100011000111 "
b11100011000111 '
1#
#114
0#
#115
b11101011000101 $
b11101011000101 &
b111010 !
b111010 (
b11100111000110 "
b11100111000110 '
1#
#116
0#
#117
b11101111000100 $
b11101111000100 &
b111011 !
b111011 (
b11101011000101 "
b11101011000101 '
1#
#118
0#
#119
b11110011000011 $
b11110011000011 &
b111100 !
b111100 (
b11101111000100 "
b11101111000100 '
1#
#120
0#
#121
b11110111000010 $
b11110111000010 &
b111101 !
b111101 (
b11110011000011 "
b11110011000011 '
1#
#122
0#
#123
b11111011000001 $
b11111011000001 &
b111110 !
b111110 (
b11110111000010 "
b11110111000010 '
1#
#124
0#
#125
b11111111000000 $
b11111111000000 &
b111111 !
b111111 (
b11111011000001 "
b11111011000001 '
1#
#126
0#
#127
b100000010111111 $
b100000010111111 &
b1000000 !
b1000000 (
b11111111000000 "
b11111111000000 '
1#
#128
0#
#129
b100000110111110 $
b100000110111110 &
b1000001 !
b1000001 (
b100000010111111 "
b100000010111111 '
1#
#130
0#
#131
b100001010111101 $
b100001010111101 &
b1000010 !
b1000010 (
b100000110111110 "
b100000110111110 '
1#
#132
0#
#133
b100001110111100 $
b100001110111100 &
b1000011 !
b1000011 (
b100001010111101 "
b100001010111101 '
1#
#134
0#
#135
b100010010111011 $
b100010010111011 &
b1000100 !
b1000100 (
b100001110111100 "
b100001110111100 '
1#
#136
0#
#137
b100010110111010 $
b100010110111010 &
b1000101 !
b1000101 (
b100010010111011 "
b100010010111011 '
1#
#138
0#
#139
b100011010111001 $
b100011010111001 &
b1000110 !
b1000110 (
b100010110111010 "
b100010110111010 '
1#
#140
0#
#141
b100011110111000 $
b100011110111000 &
b1000111 !
b1000111 (
b100011010111001 "
b100011010111001 '
1#
#142
0#
#143
b100100010110111 $
b100100010110111 &
b1001000 !
b1001000 (
b100011110111000 "
b100011110111000 '
1#
#144
0#
#145
b100100110110110 $
b100100110110110 &
b1001001 !
b1001001 (
b100100010110111 "
b100100010110111 '
1#
#146
0#
#147
b100101010110101 $
b100101010110101 &
b1001010 !
b1001010 (
b100100110110110 "
b100100110110110 '
1#
#148
0#
#149
b100101110110100 $
b100101110110100 &
b1001011 !
b1001011 (
b100101010110101 "
b100101010110101 '
1#
#150
0#
#151
b100110010110011 $
b100110010110011 &
b1001100 !
b1001100 (
b100101110110100 "
b100101110110100 '
1#
#152
0#
#153
b100110110110010 $
b100110110110010 &
b1001101 !
b1001101 (
b100110010110011 "
b100110010110011 '
1#
#154
0#
#155
b100111010110001 $
b100111010110001 &
b1001110 !
b1001110 (
b100110110110010 "
b100110110110010 '
1#
#156
0#
#157
b100111110110000 $
b100111110110000 &
b1001111 !
b1001111 (
b100111010110001 "
b100111010110001 '
1#
#158
0#
#159
b101000010101111 $
b101000010101111 &
b1010000 !
b1010000 (
b100111110110000 "
b100111110110000 '
1#
#160
0#
#161
b101000110101110 $
b101000110101110 &
b1010001 !
b1010001 (
b101000010101111 "
b101000010101111 '
1#
#162
0#
#163
b101001010101101 $
b101001010101101 &
b1010010 !
b1010010 (
b101000110101110 "
b101000110101110 '
1#
#164
0#
#165
b101001110101100 $
b101001110101100 &
b1010011 !
b1010011 (
b101001010101101 "
b101001010101101 '
1#
#166
0#
#167
b101010010101011 $
b101010010101011 &
b1010100 !
b1010100 (
b101001110101100 "
b101001110101100 '
1#
#168
0#
#169
b101010110101010 $
b101010110101010 &
b1010101 !
b1010101 (
b101010010101011 "
b101010010101011 '
1#
#170
0#
#171
b101011010101001 $
b101011010101001 &
b1010110 !
b1010110 (
b101010110101010 "
b101010110101010 '
1#
#172
0#
#173
b101011110101000 $
b101011110101000 &
b1010111 !
b1010111 (
b101011010101001 "
b101011010101001 '
1#
#174
0#
#175
b101100010100111 $
b101100010100111 &
b1011000 !
b1011000 (
b101011110101000 "
b101011110101000 '
1#
#176
0#
#177
b101100110100110 $
b101100110100110 &
b1011001 !
b1011001 (
b101100010100111 "
b101100010100111 '
1#
#178
0#
#179
b101101010100101 $
b101101010100101 &
b1011010 !
b1011010 (
b101100110100110 "
b101100110100110 '
1#
#180
0#
#181
b101101110100100 $
b101101110100100 &
b1011011 !
b1011011 (
b101101010100101 "
b101101010100101 '
1#
#182
0#
#183
b101110010100011 $
b101110010100011 &
b1011100 !
b1011100 (
b101101110100100 "
b101101110100100 '
1#
#184
0#
#185
b101110110100010 $
b101110110100010 &
b1011101 !
b1011101 (
b101110010100011 "
b101110010100011 '
1#
#186
0#
#187
b101111010100001 $
b101111010100001 &
b1011110 !
b1011110 (
b101110110100010 "
b101110110100010 '
1#
#188
0#
#189
b101111110100000 $
b101111110100000 &
b1011111 !
b1011111 (
b101111010100001 "
b101111010100001 '
1#
#190
0#
#191
b110000010011111 $
b110000010011111 &
b1100000 !
b1100000 (
b101111110100000 "
b101111110100000 '
1#
#192
0#
#193
b110000110011110 $
b110000110011110 &
b1100001 !
b1100001 (
b110000010011111 "
b110000010011111 '
1#
#194
0#
#195
b110001010011101 $
b110001010011101 &
b1100010 !
b1100010 (
b110000110011110 "
b110000110011110 '
1#
#196
0#
#197
b110001110011100 $
b110001110011100 &
b1100011 !
b1100011 (
b110001010011101 "
b110001010011101 '
1#
#198
0#
#199
b110010010011011 $
b110010010011011 &
b1100100 !
b1100100 (
b110001110011100 "
b110001110011100 '
1#
#200
0#
#201
b110010110011010 $
b110010110011010 &
b1100101 !
b1100101 (
b110010010011011 "
b110010010011011 '
1#
#202
0#
#203
b110011010011001 $
b110011010011001 &
b1100110 !
b1100110 (
b110010110011010 "
b110010110011010 '
1#
#204
0#
#205
b110011110011000 $
b110011110011000 &
b1100111 !
b1100111 (
b110011010011001 "
b110011010011001 '
1#
#206
0#
#207
b110100010010111 $
b110100010010111 &
b1101000 !
b1101000 (
b110011110011000 "
b110011110011000 '
1#
#208
0#
#209
b110100110010110 $
b110100110010110 &
b1101001 !
b1101001 (
b110100010010111 "
b110100010010111 '
1#
#210
0#
#211
b110101010010101 $
b110101010010101 &
b1101010 !
b1101010 (
b110100110010110 "
b110100110010110 '
1#
#212
0#
#213
b110101110010100 $
b110101110010100 &
b1101011 !
b1101011 (
b110101010010101 "
b110101010010101 '
1#
#214
0#
#215
b110110010010011 $
b110110010010011 &
b1101100 !
b1101100 (
b110101110010100 "
b110101110010100 '
1#
#216
0#
#217
b110110110010010 $
b110110110010010 &
b1101101 !
b1101101 (
b110110010010011 "
b110110010010011 '
1#
#218
0#
#219
b110111010010001 $
b110111010010001 &
b1101110 !
b1101110 (
b110110110010010 "
b110110110010010 '
1#
#220
0#
#221
b110111110010000 $
b110111110010000 &
b1101111 !
b1101111 (
b110111010010001 "
b110111010010001 '
1#
#222
0#
#223
b111000010001111 $
b111000010001111 &
b1110000 !
b1110000 (
b110111110010000 "
b110111110010000 '
1#
#224
0#
#225
b111000110001110 $
b111000110001110 &
b1110001 !
b1110001 (
b111000010001111 "
b111000010001111 '
1#
#226
0#
#227
b111001010001101 $
b111001010001101 &
b1110010 !
b1110010 (
b111000110001110 "
b111000110001110 '
1#
#228
0#
#229
b111001110001100 $
b111001110001100 &
b1110011 !
b1110011 (
b111001010001101 "
b111001010001101 '
1#
#230
0#
#231
b111010010001011 $
b111010010001011 &
b1110100 !
b1110100 (
b111001110001100 "
b111001110001100 '
1#
#232
0#
#233
b111010110001010 $
b111010110001010 &
b1110101 !
b1110101 (
b111010010001011 "
b111010010001011 '
1#
#234
0#
#235
b111011010001001 $
b111011010001001 &
b1110110 !
b1110110 (
b111010110001010 "
b111010110001010 '
1#
#236
0#
#237
b111011110001000 $
b111011110001000 &
b1110111 !
b1110111 (
b111011010001001 "
b111011010001001 '
1#
#238
0#
#239
b111100010000111 $
b111100010000111 &
b1111000 !
b1111000 (
b111011110001000 "
b111011110001000 '
1#
#240
0#
#241
b111100110000110 $
b111100110000110 &
b1111001 !
b1111001 (
b111100010000111 "
b111100010000111 '
1#
#242
0#
#243
b111101010000101 $
b111101010000101 &
b1111010 !
b1111010 (
b111100110000110 "
b111100110000110 '
1#
#244
0#
#245
b111101110000100 $
b111101110000100 &
b1111011 !
b1111011 (
b111101010000101 "
b111101010000101 '
1#
#246
0#
#247
b111110010000011 $
b111110010000011 &
b1111100 !
b1111100 (
b111101110000100 "
b111101110000100 '
1#
#248
0#
#249
b111110110000010 $
b111110110000010 &
b1111101 !
b1111101 (
b111110010000011 "
b111110010000011 '
1#
#250
0#
#251
b111111010000001 $
b111111010000001 &
b1111110 !
b1111110 (
b111110110000010 "
b111110110000010 '
1#
#252
0#
#253
b111111110000000 $
b111111110000000 &
b1111111 !
b1111111 (
b111111010000001 "
b111111010000001 '
1#
#254
0#
#255
b1000000001111111 $
b1000000001111111 &
b10000000 !
b10000000 (
b111111110000000 "
b111111110000000 '
1#
#256
0#
#257
b1000000101111110 $
b1000000101111110 &
b10000001 !
b10000001 (
b1000000001111111 "
b1000000001111111 '
1#
#258
0#
#259
b1000001001111101 $
b1000001001111101 &
b10000010 !
b10000010 (
b1000000101111110 "
b1000000101111110 '
1#
#260
0#
#261
b1000001101111100 $
b1000001101111100 &
b10000011 !
b10000011 (
b1000001001111101 "
b1000001001111101 '
1#
#262
0#
#263
b1000010001111011 $
b1000010001111011 &
b10000100 !
b10000100 (
b1000001101111100 "
b1000001101111100 '
1#
#264
0#
#265
b1000010101111010 $
b1000010101111010 &
b10000101 !
b10000101 (
b1000010001111011 "
b1000010001111011 '
1#
#266
0#
#267
b1000011001111001 $
b1000011001111001 &
b10000110 !
b10000110 (
b1000010101111010 "
b1000010101111010 '
1#
#268
0#
#269
b1000011101111000 $
b1000011101111000 &
b10000111 !
b10000111 (
b1000011001111001 "
b1000011001111001 '
1#
#270
0#
#271
b1000100001110111 $
b1000100001110111 &
b10001000 !
b10001000 (
b1000011101111000 "
b1000011101111000 '
1#
#272
0#
#273
b1000100101110110 $
b1000100101110110 &
b10001001 !
b10001001 (
b1000100001110111 "
b1000100001110111 '
1#
#274
0#
#275
b1000101001110101 $
b1000101001110101 &
b10001010 !
b10001010 (
b1000100101110110 "
b1000100101110110 '
1#
#276
0#
#277
b1000101101110100 $
b1000101101110100 &
b10001011 !
b10001011 (
b1000101001110101 "
b1000101001110101 '
1#
#278
0#
#279
b1000110001110011 $
b1000110001110011 &
b10001100 !
b10001100 (
b1000101101110100 "
b1000101101110100 '
1#
#280
0#
#281
b1000110101110010 $
b1000110101110010 &
b10001101 !
b10001101 (
b1000110001110011 "
b1000110001110011 '
1#
#282
0#
#283
b1000111001110001 $
b1000111001110001 &
b10001110 !
b10001110 (
b1000110101110010 "
b1000110101110010 '
1#
#284
0#
#285
b1000111101110000 $
b1000111101110000 &
b10001111 !
b10001111 (
b1000111001110001 "
b1000111001110001 '
1#
#286
0#
#287
b1001000001101111 $
b1001000001101111 &
b10010000 !
b10010000 (
b1000111101110000 "
b1000111101110000 '
1#
#288
0#
#289
b1001000101101110 $
b1001000101101110 &
b10010001 !
b10010001 (
b1001000001101111 "
b1001000001101111 '
1#
#290
0#
#291
b1001001001101101 $
b1001001001101101 &
b10010010 !
b10010010 (
b1001000101101110 "
b1001000101101110 '
1#
#292
0#
#293
b1001001101101100 $
b1001001101101100 &
b10010011 !
b10010011 (
b1001001001101101 "
b1001001001101101 '
1#
#294
0#
#295
b1001010001101011 $
b1001010001101011 &
b10010100 !
b10010100 (
b1001001101101100 "
b1001001101101100 '
1#
#296
0#
#297
b1001010101101010 $
b1001010101101010 &
b10010101 !
b10010101 (
b1001010001101011 "
b1001010001101011 '
1#
#298
0#
#299
b1001011001101001 $
b1001011001101001 &
b10010110 !
b10010110 (
b1001010101101010 "
b1001010101101010 '
1#
#300
0#
#301
b1001011101101000 $
b1001011101101000 &
b10010111 !
b10010111 (
b1001011001101001 "
b1001011001101001 '
1#
#302
0#
#303
b1001100001100111 $
b1001100001100111 &
b10011000 !
b10011000 (
b1001011101101000 "
b1001011101101000 '
1#
#304
0#
#305
b1001100101100110 $
b1001100101100110 &
b10011001 !
b10011001 (
b1001100001100111 "
b1001100001100111 '
1#
#306
0#
#307
b1001101001100101 $
b1001101001100101 &
b10011010 !
b10011010 (
b1001100101100110 "
b1001100101100110 '
1#
#308
0#
#309
b1001101101100100 $
b1001101101100100 &
b10011011 !
b10011011 (
b1001101001100101 "
b1001101001100101 '
1#
#310
0#
#311
b1001110001100011 $
b1001110001100011 &
b10011100 !
b10011100 (
b1001101101100100 "
b1001101101100100 '
1#
#312
0#
#313
b1001110101100010 $
b1001110101100010 &
b10011101 !
b10011101 (
b1001110001100011 "
b1001110001100011 '
1#
#314
0#
#315
b1001111001100001 $
b1001111001100001 &
b10011110 !
b10011110 (
b1001110101100010 "
b1001110101100010 '
1#
#316
0#
#317
b1001111101100000 $
b1001111101100000 &
b10011111 !
b10011111 (
b1001111001100001 "
b1001111001100001 '
1#
#318
0#
#319
b1010000001011111 $
b1010000001011111 &
b10100000 !
b10100000 (
b1001111101100000 "
b1001111101100000 '
1#
#320
0#
#321
b1010000101011110 $
b1010000101011110 &
b10100001 !
b10100001 (
b1010000001011111 "
b1010000001011111 '
1#
#322
0#
#323
b1010001001011101 $
b1010001001011101 &
b10100010 !
b10100010 (
b1010000101011110 "
b1010000101011110 '
1#
#324
0#
#325
b1010001101011100 $
b1010001101011100 &
b10100011 !
b10100011 (
b1010001001011101 "
b1010001001011101 '
1#
#326
0#
#327
b1010010001011011 $
b1010010001011011 &
b10100100 !
b10100100 (
b1010001101011100 "
b1010001101011100 '
1#
#328
0#
#329
b1010010101011010 $
b1010010101011010 &
b10100101 !
b10100101 (
b1010010001011011 "
b1010010001011011 '
1#
#330
0#
#331
b1010011001011001 $
b1010011001011001 &
b10100110 !
b10100110 (
b1010010101011010 "
b1010010101011010 '
1#
#332
0#
#333
b1010011101011000 $
b1010011101011000 &
b10100111 !
b10100111 (
b1010011001011001 "
b1010011001011001 '
1#
#334
0#
#335
b1010100001010111 $
b1010100001010111 &
b10101000 !
b10101000 (
b1010011101011000 "
b1010011101011000 '
1#
#336
0#
#337
b1010100101010110 $
b1010100101010110 &
b10101001 !
b10101001 (
b1010100001010111 "
b1010100001010111 '
1#
#338
0#
#339
b1010101001010101 $
b1010101001010101 &
b10101010 !
b10101010 (
b1010100101010110 "
b1010100101010110 '
1#
#340
0#
#341
b1010101101010100 $
b1010101101010100 &
b10101011 !
b10101011 (
b1010101001010101 "
b1010101001010101 '
1#
#342
0#
#343
b1010110001010011 $
b1010110001010011 &
b10101100 !
b10101100 (
b1010101101010100 "
b1010101101010100 '
1#
#344
0#
#345
b1010110101010010 $
b1010110101010010 &
b10101101 !
b10101101 (
b1010110001010011 "
b1010110001010011 '
1#
#346
0#
#347
b1010111001010001 $
b1010111001010001 &
b10101110 !
b10101110 (
b1010110101010010 "
b1010110101010010 '
1#
#348
0#
#349
b1010111101010000 $
b1010111101010000 &
b10101111 !
b10101111 (
b1010111001010001 "
b1010111001010001 '
1#
#350
0#
#351
b1011000001001111 $
b1011000001001111 &
b10110000 !
b10110000 (
b1010111101010000 "
b1010111101010000 '
1#
#352
0#
#353
b1011000101001110 $
b1011000101001110 &
b10110001 !
b10110001 (
b1011000001001111 "
b1011000001001111 '
1#
#354
0#
#355
b1011001001001101 $
b1011001001001101 &
b10110010 !
b10110010 (
b1011000101001110 "
b1011000101001110 '
1#
#356
0#
#357
b1011001101001100 $
b1011001101001100 &
b10110011 !
b10110011 (
b1011001001001101 "
b1011001001001101 '
1#
#358
0#
#359
b1011010001001011 $
b1011010001001011 &
b10110100 !
b10110100 (
b1011001101001100 "
b1011001101001100 '
1#
#360
0#
#361
b1011010101001010 $
b1011010101001010 &
b10110101 !
b10110101 (
b1011010001001011 "
b1011010001001011 '
1#
#362
0#
#363
b1011011001001001 $
b1011011001001001 &
b10110110 !
b10110110 (
b1011010101001010 "
b1011010101001010 '
1#
#364
0#
#365
b1011011101001000 $
b1011011101001000 &
b10110111 !
b10110111 (
b1011011001001001 "
b1011011001001001 '
1#
#366
0#
#367
b1011100001000111 $
b1011100001000111 &
b10111000 !
b10111000 (
b1011011101001000 "
b1011011101001000 '
1#
#368
0#
#369
b1011100101000110 $
b1011100101000110 &
b10111001 !
b10111001 (
b1011100001000111 "
b1011100001000111 '
1#
#370
0#
#371
b1011101001000101 $
b1011101001000101 &
b10111010 !
b10111010 (
b1011100101000110 "
b1011100101000110 '
1#
#372
0#
#373
b1011101101000100 $
b1011101101000100 &
b10111011 !
b10111011 (
b1011101001000101 "
b1011101001000101 '
1#
#374
0#
#375
b1011110001000011 $
b1011110001000011 &
b10111100 !
b10111100 (
b1011101101000100 "
b1011101101000100 '
1#
#376
0#
#377
b1011110101000010 $
b1011110101000010 &
b10111101 !
b10111101 (
b1011110001000011 "
b1011110001000011 '
1#
#378
0#
#379
b1011111001000001 $
b1011111001000001 &
b10111110 !
b10111110 (
b1011110101000010 "
b1011110101000010 '
1#
#380
0#
#381
b1011111101000000 $
b1011111101000000 &
b10111111 !
b10111111 (
b1011111001000001 "
b1011111001000001 '
1#
#382
0#
#383
b1100000000111111 $
b1100000000111111 &
b11000000 !
b11000000 (
b1011111101000000 "
b1011111101000000 '
1#
#384
0#
#385
b1100000100111110 $
b1100000100111110 &
b11000001 !
b11000001 (
b1100000000111111 "
b1100000000111111 '
1#
#386
0#
#387
b1100001000111101 $
b1100001000111101 &
b11000010 !
b11000010 (
b1100000100111110 "
b1100000100111110 '
1#
#388
0#
#389
b1100001100111100 $
b1100001100111100 &
b11000011 !
b11000011 (
b1100001000111101 "
b1100001000111101 '
1#
#390
0#
#391
b1100010000111011 $
b1100010000111011 &
b11000100 !
b11000100 (
b1100001100111100 "
b1100001100111100 '
1#
#392
0#
#393
b1100010100111010 $
b1100010100111010 &
b11000101 !
b11000101 (
b1100010000111011 "
b1100010000111011 '
1#
#394
0#
#395
b1100011000111001 $
b1100011000111001 &
b11000110 !
b11000110 (
b1100010100111010 "
b1100010100111010 '
1#
#396
0#
#397
b1100011100111000 $
b1100011100111000 &
b11000111 !
b11000111 (
b1100011000111001 "
b1100011000111001 '
1#
#398
0#
#399
b1100100000110111 $
b1100100000110111 &
b11001000 !
b11001000 (
b1100011100111000 "
b1100011100111000 '
1#
#400
0#
#401
b1100100100110110 $
b1100100100110110 &
b11001001 !
b11001001 (
b1100100000110111 "
b1100100000110111 '
1#
#402
0#
#403
b1100101000110101 $
b1100101000110101 &
b11001010 !
b11001010 (
b1100100100110110 "
b1100100100110110 '
1#
#404
0#
#405
b1100101100110100 $
b1100101100110100 &
b11001011 !
b11001011 (
b1100101000110101 "
b1100101000110101 '
1#
#406
0#
#407
b1100110000110011 $
b1100110000110011 &
b11001100 !
b11001100 (
b1100101100110100 "
b1100101100110100 '
1#
#408
0#
#409
b1100110100110010 $
b1100110100110010 &
b11001101 !
b11001101 (
b1100110000110011 "
b1100110000110011 '
1#
#410
0#
#411
b1100111000110001 $
b1100111000110001 &
b11001110 !
b11001110 (
b1100110100110010 "
b1100110100110010 '
1#
#412
0#
#413
b1100111100110000 $
b1100111100110000 &
b11001111 !
b11001111 (
b1100111000110001 "
b1100111000110001 '
1#
#414
0#
#415
b1101000000101111 $
b1101000000101111 &
b11010000 !
b11010000 (
b1100111100110000 "
b1100111100110000 '
1#
#416
0#
#417
b1101000100101110 $
b1101000100101110 &
b11010001 !
b11010001 (
b1101000000101111 "
b1101000000101111 '
1#
#418
0#
#419
b1101001000101101 $
b1101001000101101 &
b11010010 !
b11010010 (
b1101000100101110 "
b1101000100101110 '
1#
#420
0#
#421
b1101001100101100 $
b1101001100101100 &
b11010011 !
b11010011 (
b1101001000101101 "
b1101001000101101 '
1#
#422
0#
#423
b1101010000101011 $
b1101010000101011 &
b11010100 !
b11010100 (
b1101001100101100 "
b1101001100101100 '
1#
#424
0#
#425
b1101010100101010 $
b1101010100101010 &
b11010101 !
b11010101 (
b1101010000101011 "
b1101010000101011 '
1#
#426
0#
#427
b1101011000101001 $
b1101011000101001 &
b11010110 !
b11010110 (
b1101010100101010 "
b1101010100101010 '
1#
#428
0#
#429
b1101011100101000 $
b1101011100101000 &
b11010111 !
b11010111 (
b1101011000101001 "
b1101011000101001 '
1#
#430
0#
#431
b1101100000100111 $
b1101100000100111 &
b11011000 !
b11011000 (
b1101011100101000 "
b1101011100101000 '
1#
#432
0#
#433
b1101100100100110 $
b1101100100100110 &
b11011001 !
b11011001 (
b1101100000100111 "
b1101100000100111 '
1#
#434
0#
#435
b1101101000100101 $
b1101101000100101 &
b11011010 !
b11011010 (
b1101100100100110 "
b1101100100100110 '
1#
#436
0#
#437
b1101101100100100 $
b1101101100100100 &
b11011011 !
b11011011 (
b1101101000100101 "
b1101101000100101 '
1#
#438
0#
#439
b1101110000100011 $
b1101110000100011 &
b11011100 !
b11011100 (
b1101101100100100 "
b1101101100100100 '
1#
#440
0#
#441
b1101110100100010 $
b1101110100100010 &
b11011101 !
b11011101 (
b1101110000100011 "
b1101110000100011 '
1#
#442
0#
#443
b1101111000100001 $
b1101111000100001 &
b11011110 !
b11011110 (
b1101110100100010 "
b1101110100100010 '
1#
#444
0#
