Code/execute.v
/*
	Module written by Rahul Kejriwal
	CS14B023

	Synchronous module for execution and result storage 
*/

module executeAndStoreBack(
		input clk,
		input rst,

		input[ 3:0] opcode,
		input[ 3:0] destReg,
		input[15:0] srcVal1,
		input[15:0] srcVal2,
		input[ 7:0] memAddr, 
		input used1,
		input used2,

		output[ 3:0] destRegStore,
		output[15:0] destVal,
		output storeNow,
		input storeDone,

		output[ 7:0] memAddrLoadStore,
		output[15:0] memValueStore,

		input[15:0] memValueLoad,
		input valueReady,
		output readReq,
		output writeReq,

		output[15:0] ProcessorStatusWord,
	
		output powerdown
	);

	reg[ 3:0] destRegStore;
	reg[ 7:0] memAddrLoadStore;
	reg[15:0] destVal, memValueStore;

	reg[15:0] LastComputedValue;
	reg[15:0] ProcessorStatusWord;

	reg readReq, storeNow, writeReq;
	reg[15:0] val1, val2;
	reg powerdown;

	initial begin
		destRegStore 		= 4'b0;
		memAddrLoadStore	= 8'b0;
		memValueStore		= 16'b0;
		destVal				= 16'b0;
		
		LastComputedValue   = 16'b0;
		ProcessorStatusWord = 16'b0;		
		
		readReq = 0;
		storeNow = 0;
		val1 = 16'b0;
		val2 = 16'b0;
		powerdown = 0;
	end

	always @(posedge rst) begin
		destRegStore 		= 4'b0;
		memAddrLoadStore	= 8'b0;
		memValueStore		= 16'b0;
		destVal		        = 16'b0;
		
		LastComputedValue   = 16'b0;
		ProcessorStatusWord = 16'b0;
		
		readReq = 0;
		storeNow = 0;
		val1 = 16'b0;
		val2 = 16'b0;
	end

	always @(posedge clk) begin
		// Write Sync Signal for register writes
		storeNow = 0;
		writeReq = 0;
		
		#1
		ProcessorStatusWord = 16'b0;

		// Checking if src1 was being computed
		#1 if(used1)
			val1 = LastComputedValue;
		else
			val1 = srcVal1;			

		// Checking if src2 was being computed
		if(used2)
			val2 = LastComputedValue;
		else
			val2 = srcVal2;			

		// Execute appropriate action for the opcode
		#0 case(opcode)
			// NOP
			 0: begin
			 		// Doing nothing
			 		$display("Doing nothing");
			 	end 

			// HLT
			 1: begin
			 		$display("HLTing");
			 		powerdown = 1;
			 	end

			// ADD
			 2: begin
			        {ProcessorStatusWord[15],destVal} = val1 + val2;
				 	
				    if(val1[15] == val2[15] && destVal[15] != val1[15])
			 			ProcessorStatusWord[14] = 1;
			 	end

			// SUB
			 3: begin
				 	{ProcessorStatusWord[15],destVal} = val1 - val2;
				 	
				    if(val1[15] != val2[15] && destVal[15] != val1[15])
				 		ProcessorStatusWord[14] = 1;
			 	end 
			 
			// MUL
			 4: begin
				 	{ProcessorStatusWord[15],destVal} = val1 * val2;
				 							 	
			 	end

			// SL
			 5: begin
				 	{ProcessorStatusWord[15],destVal} = val1 << val2;		 	
			 	end

			// SR
			 6: begin
			 		{ProcessorStatusWord[15],destVal} = val1 >> val2;
			 	end
			 
			// AND
			 7: begin
			 		destVal = val1 & val2;
			 	end

			// OR
			 8: begin
			 		destVal = val1 | val2;
			 	end
			 
			// NOT
			 9: begin
			 		// ignores val2
				 	destVal = ~val1;
				end
			
			// XOR
			10: begin
					destVal = val1 ^ val2;
				end

			// LOAD
			14: begin
					memAddrLoadStore = memAddr;
					readReq = 1'b1;
				end

			// STORE
			15: begin
					memAddrLoadStore = memAddr;
					memValueStore = val1;
					writeReq = 1;
				end

			default:begin
						$display("Failure in execute unit!");
						powerdown = 1;
					end
		endcase

		// Set register address to write to and send signal to write to reg file
		if(opcode >= 2 && opcode <= 10) begin
			destRegStore = destReg;
			storeNow = 1;

		 	if(destVal == 0)
				ProcessorStatusWord[13] = 1;	
			
			#1 LastComputedValue = destVal;
		end
	end

	// Sent signal to read mem location. Waiting for signal that value is ready.
	always @(posedge valueReady) begin
		readReq = 1'b0;
		destVal = memValueLoad;
		if(destVal == 0)
			ProcessorStatusWord[13] = 1;		

		destRegStore = destReg;
		storeNow = 1;			
		#1 LastComputedValue = destVal;
	end

endmodule

Code/regfile.v
/*
	Module written by Rahul Kejriwal
	CS14B023

	Currently, asynchronous RegisterFile that uses clk only for modifications to inuse bits.
*/

module RegisterFile(
		input clk,
		input rst,

		input[3:0] srcReg1,
		input[3:0] srcReg2,
		input[3:0] nextDestReg,
		
		input[3:0] destReg,
		input[15:0] destVal,
		input storeNow,
		output storeDone,
		
		output[15:0] srcRegVal1,
		output[15:0] srcRegVal2,
		output inuse1,
		output inuse2
	);
	
	// Array of Registers 
	reg[15:0] r[0:15];
	reg inuse[0:15];

	// Declare outputs as regs
	reg[15:0] srcRegVal1, srcRegVal2;
	reg inuse1, inuse2;

	reg storeDone;

	/*
		For loop initialization
	*/
	integer i;

	/*
		Initialize all registers and inuse bits to 0.
	*/
	initial begin
		for(i=0; i<16; i++) begin
			r[i] = 16'b0;
			inuse[i] = 1'b0;
		end

		srcRegVal1 = 16'b0;
		srcRegVal2 = 16'b0;
		inuse1 = 0;
		inuse2 = 0;
		
		storeDone = 0;
		$monitor($time,, {"Regs:",
			"\n 0:%x %b, 1:%x %b, 2:%x %b, 3:%x %b, 4:%x %b,",
			"\n 5:%x %b, 6:%x %b, 7:%x %b, 8:%x %b,",
			"\n 9:%x %b, 10:%x %b, 11:%x %b, 12:%x %b,",
			"\n 13:%x %b, 14:%x %b, 15:%x %b"}, 
			r[0], inuse[0], r[1], inuse[1], r[2], inuse[2], r[3], inuse[3], r[4], inuse[4], 
			r[5], inuse[5], r[6], inuse[6], r[7], inuse[7], r[8], inuse[8], r[9], inuse[9], 
			r[10], inuse[10], r[11], inuse[11], r[12], inuse[12], r[13], inuse[13], r[14], inuse[14], r[15], inuse[15]);
	end

	/*
		Initialize all registers and inuse bits to 0 on reset.
	*/
	always @(posedge rst) begin
		for(i=0; i<16; i++) begin
			r[i] = 16'b0;
			inuse[i] = 1'b0;
		end		

		srcRegVal1 = 16'b0;
		srcRegVal2 = 16'b0;
		inuse1 = 0;
		inuse2 = 0;
		storeDone = 0;
	end

	/*
		When any input changes, recompute outputs for 'Decode & Fetch Operand' stage
	*/
	always @(srcReg1 or srcReg2 or nextDestReg) begin
		srcRegVal1 = r[srcReg1];
		srcRegVal2 = r[srcReg2];
		inuse1 	   = inuse[srcReg1];
		inuse2 	   = inuse[srcReg2];
	end

	/*
		Set inuse at posedge
	*/
	always @(posedge clk) begin
		
		for(i=0;i<16;i++)
			inuse[i] = 1'b0;
		
		inuse[nextDestReg] = 1'b1;
	end

	/*
		Issue: [FIXED] Consider 2 instruction - 
			I1:	add R3, R1, R2
			I2:	add R3, R4, R5

			I1 will reset inuse[R3] and I2 will set inuse[R3] leading to ??
	
		Fix: Done
	*/
	always @(posedge storeNow) begin
		storeDone = 0;
		r[destReg] = destVal;
		storeDone = 1;
	end

endmodule

Code/decoder.v
/*
	Module written by Rahul Kejriwal
	CS14B023

	Synchronous module to decode instructions and fetch register values
*/

module decodeAndFetchOperands(
		input clk,
		input rst,

		// Input from Fetch Instruction unit
		input[15:0] instr,

		// Input ports from RegFile
		input[15:0] srcRegVal1,
		input[15:0] srcRegVal2,
		input inuse1,
		input inuse2,

		// Output ports to RegFile
		output[ 3:0] srcReg1,
		output[ 3:0] srcReg2,
		output[ 3:0] nextDestReg,

		// Output ports to Execute unit
		output[ 3:0] opcode,
		output[ 3:0] destReg,
		output[15:0] srcVal1,
		output[15:0] srcVal2,
		output[ 7:0] memAddr, 
		output used1,
		output used2
	);


	/*
		Declare all outputs as registers
	*/
	reg[ 3:0] srcReg1, srcReg2, nextDestReg;

	reg[ 3:0] opcode, destReg;
	reg[15:0] srcVal1, srcVal2;
	reg[ 7:0] memAddr;
	reg used1, used2;

	/*
		Zero all registers at start
	*/
	initial begin
		srcReg1 	= 4'b0; 	
		srcReg2 	= 4'b0; 	
		nextDestReg = 4'b0; 	
	
		opcode 		= 4'b0;
		destReg		= 4'b0;
		srcVal1		= 16'b0;
		srcVal2		= 16'b0;
		memAddr		= 8'b0;
		used1		= 0;
		used2		= 0;		
	end

	/*
		Zero all registers on reset
	*/
	always @(posedge rst) begin
		srcReg1 	= 4'b0; 	
		srcReg2 	= 4'b0; 	
		nextDestReg = 4'b0; 	
	
		opcode 		= 4'b0;
		destReg		= 4'b0;
		srcVal1		= 16'b0;
		srcVal2		= 16'b0;
		memAddr		= 8'b0;
		used1		= 0;
		used2		= 0;
	end

	/*
		Operation Logic
	*/
	always @(posedge clk) begin
		#1
		opcode 		= instr[ 12+:4];
		// $display("Opcode %b", opcode);

		// If LOAD instruction
		if(opcode == 4'b1110) begin
			memAddr		= instr[ 4+:8];
			nextDestReg = instr[ 0+:4];
			destReg 	= instr[ 0+:4];
		end
		// If STORE instruction
		else if(opcode == 4'b1111) begin
			memAddr		= instr[ 4+:8];
			nextDestReg = instr[ 0+:4];
			destReg 	= instr[ 0+:4];			

			// Send addr to regfile
			srcReg1 	= instr[ 0+:4];
		end
		// For other instructions
		else begin
			nextDestReg = instr[ 8+:4];
			destReg 	= instr[ 8+:4];
			srcReg1 	= instr[ 4+:4];
			srcReg2 	= instr[ 0+:4];
		end
	end

	/*
		On Feedback from Register File
	*/
	always @(srcRegVal1 or srcRegVal2 or inuse1 or inuse2) begin
		srcVal1 = srcRegVal1;
		srcVal2 = srcRegVal2;
		used1   = inuse1;
		used2   = inuse2;
	end

endmodule

Code/fetch.v
/*
	Module written by Rahul Kejriwal
	CS14B023

	Synchronous module to fetch instructions
*/

module fetchInstruction(
		input clk,
		input rst,

		output[7:0] prog_ctr,
		input[15:0] instr,

		output[15:0] curr_instr
	);

	// Program Counter
	reg[ 7:0] prog_ctr;
	// Instruction Register
	reg[15:0] curr_instr;

	initial begin
 		prog_ctr	= 8'b0;
 		curr_instr	= 16'b0;		
	end

 	always @(posedge rst) begin
 		prog_ctr	= 8'b0;
 		curr_instr	= 16'b0;
 	end

 	always @(posedge clk) begin
	 	curr_instr = instr;
 		prog_ctr += 1;
 	end
endmodule

Code/processor.v
/*
	Module written by Rahul Kejriwal
	CS14B023

	Top Level Module for the Processor
*/

`include "Code/fetch.v"
`include "Code/decoder.v"
`include "Code/regfile.v"
`include "Code/execute.v"

module Processor(
		input clk,
		input rst,

		output[7:0] instr_addr,
		input[15:0] instr,

		output[ 7:0] memAddrLoadStore,
		output[15:0] memStoreVal,
		input[ 15:0] memLoadVal,

		input valueReady,
		output readReq,
		output writeReq,

		output powerdown
	);
	
	reg[15:0] PSW;

	wire[15:0] curr_instr, srcRegVal1, srcRegVal2, srcVal1, srcVal2, destVal, pswWire;
	wire[ 3:0] srcReg1, srcReg2, opcode, destReg, nextDestReg, destRegStore;
	wire[ 7:0] memAddr;

	// Fetch Unit	
	fetchInstruction I(clk, rst, instr_addr, instr, curr_instr);	
	
	// Decode Unit
	decodeAndFetchOperands D(clk, rst, 
		curr_instr, 
		srcRegVal1, srcRegVal2, inuse1, inuse2,
		srcReg1, srcReg2, nextDestReg,
		opcode, destReg, srcVal1, srcVal2, memAddr, used1, used2);
	
	// Register File
	RegisterFile R(clk, rst,
		srcReg1, srcReg2, nextDestReg,
		destRegStore, destVal, storeNow, storeDone,
		srcRegVal1, srcRegVal2, inuse1, inuse2);
	
	//Execute Unit
	executeAndStoreBack E(clk, rst,
		opcode, destReg, srcVal1, srcVal2, memAddr, used1, used2,
		destRegStore, destVal, storeNow, storeDone,
		memAddrLoadStore, memStoreVal,
		memLoadVal, valueReady, readReq, writeReq,
		pswWire, 
		powerdown);

	initial begin
		PSW = 16'b0;
	end

	always @(rst) begin
		PSW = 16'b0;
	end

	always @(posedge clk) begin
		PSW = pswWire;
	end
endmodule

Testbench/processor_testbench.v
/*
	Module written by Rahul Kejriwal
	CS14B023

	TestBench for the Processor
*/

`include "Code/processor.v"

module processor_TestBench(
		output clk,
		output rst,

		input[7:0] instr_addr,
		output[15:0] instr,

		input[ 7:0] memAddrLoadStore,
		input[15:0] memStoreVal,
		output[ 15:0] memLoadVal,

		output valueReady,
		input readReq,
		input writeReq,

		input powerdown
	);

	reg clk, rst, valueReady;
	reg[15:0] instr, memLoadVal;

	// Memory contents
	reg[15:0] memory[0:255];

	integer i;

	Processor P(clk, rst, instr_addr, instr,
		memAddrLoadStore, memStoreVal, memLoadVal,
		valueReady, readReq, writeReq, 
		powerdown);

	always begin
		#2 clk = ~clk;
	end

	initial begin
		$dumpfile("processor.vcd");
    	$dumpvars(0,processor_TestBench);
		$monitor($time,, "Memlocval: %b", memory[130]);

		clk = 0;
		rst = 0;
		valueReady = 0;

		// Not in use at start
		instr = 0;
		memLoadVal = 0;
	
		// Initialize memory
		for(i=0;i<255;i++)
			memory[i] = 0;

		// Define memory mapping here
		memory[0] = 16'b0000000000000000;
		memory[1] = 16'b1110100000000001;
		memory[2] = 16'b1110100000010010;
		memory[3] = 16'b0010001100100001;
		memory[4] = 16'b1111100000100011;
		memory[5] = 16'b1110100000000100;
		memory[6] = 16'b1110100000010101;
		memory[7] = 16'b0011011001000101;
		memory[8] = 16'b1111100000100110;
		memory[9] = 16'b1110100000000111;
		memory[10] = 16'b1110100000011000;
		memory[11] = 16'b0100100101111000;
		memory[12] = 16'b1111100000101001;
		memory[13] = 16'b0101100101111000;
		memory[14] = 16'b1111100000101001;
		memory[15] = 16'b0110100101111000;
		memory[16] = 16'b1111100000101001;
		memory[17] = 16'b0111100101111000;
		memory[18] = 16'b1111100000101001;
		memory[19] = 16'b1000100101111000;
		memory[20] = 16'b1111100000101001;
		memory[21] = 16'b1001100101111000;
		memory[22] = 16'b1111100000101001;
		memory[23] = 16'b1010100101111000;
		memory[24] = 16'b1111100000101001;
		memory[25] = 16'b0010001100010001;
		memory[26] = 16'b0010010000110011;
		memory[27] = 16'b1111100000100100;
		memory[28] = 16'b1110100000100001;
		memory[29] = 16'b1111100000100001;
		memory[30] = 16'b1010000100010001;
		memory[31] = 16'b1111100000100001;
		memory[32] = 16'b1110100000100001;
		memory[33] = 16'b0001000000000000;
	
		memory[128] = 1;
		memory[129] = 2;
	end

	always @(instr_addr) begin
		instr = memory[instr_addr];
	
		if(instr_addr == 33)
			$finish;
	end

	always @(posedge readReq) begin
		valueReady = 0;
		memLoadVal = memory[memAddrLoadStore];
		valueReady = 1;
	end

	always @(posedge writeReq) begin
		// $display("Writing %d to %d", memStoreVal, memAddrLoadStore);
		memory[memAddrLoadStore] = memStoreVal;
	end

	always @(posedge powerdown) begin
		$finish;
	end

endmodule

Testbench/processor.vcd
$date
	Sun Feb 19 01:02:18 2017
$end
$version
	Icarus Verilog
$end
$timescale
	1s
$end
$scope module processor_TestBench $end
$var wire 1 ! writeReq $end
$var wire 1 " readReq $end
$var wire 1 # powerdown $end
$var wire 16 $ memStoreVal [15:0] $end
$var wire 8 % memAddrLoadStore [7:0] $end
$var wire 8 & instr_addr [7:0] $end
$var reg 1 ' clk $end
$var reg 16 ( instr [15:0] $end
$var reg 16 ) memLoadVal [15:0] $end
$var reg 1 * rst $end
$var reg 1 + valueReady $end
$var integer 32 , i [31:0] $end
$scope module P $end
$var wire 1 ' clk $end
$var wire 16 - instr [15:0] $end
$var wire 16 . memLoadVal [15:0] $end
$var wire 1 * rst $end
$var wire 1 + valueReady $end
$var wire 1 ! writeReq $end
$var wire 1 / used2 $end
$var wire 1 0 used1 $end
$var wire 1 1 storeNow $end
$var wire 1 2 storeDone $end
$var wire 16 3 srcVal2 [15:0] $end
$var wire 16 4 srcVal1 [15:0] $end
$var wire 16 5 srcRegVal2 [15:0] $end
$var wire 16 6 srcRegVal1 [15:0] $end
$var wire 4 7 srcReg2 [3:0] $end
$var wire 4 8 srcReg1 [3:0] $end
$var wire 1 " readReq $end
$var wire 16 9 pswWire [15:0] $end
$var wire 1 # powerdown $end
$var wire 4 : opcode [3:0] $end
$var wire 4 ; nextDestReg [3:0] $end
$var wire 16 < memStoreVal [15:0] $end
$var wire 8 = memAddrLoadStore [7:0] $end
$var wire 8 > memAddr [7:0] $end
$var wire 1 ? inuse2 $end
$var wire 1 @ inuse1 $end
$var wire 8 A instr_addr [7:0] $end
$var wire 16 B destVal [15:0] $end
$var wire 4 C destRegStore [3:0] $end
$var wire 4 D destReg [3:0] $end
$var wire 16 E curr_instr [15:0] $end
$var reg 16 F PSW [15:0] $end
$scope module D $end
$var wire 1 ' clk $end
$var wire 1 * rst $end
$var wire 16 G srcRegVal2 [15:0] $end
$var wire 16 H srcRegVal1 [15:0] $end
$var wire 1 ? inuse2 $end
$var wire 1 @ inuse1 $end
$var wire 16 I instr [15:0] $end
$var reg 4 J destReg [3:0] $end
$var reg 8 K memAddr [7:0] $end
$var reg 4 L nextDestReg [3:0] $end
$var reg 4 M opcode [3:0] $end
$var reg 4 N srcReg1 [3:0] $end
$var reg 4 O srcReg2 [3:0] $end
$var reg 16 P srcVal1 [15:0] $end
$var reg 16 Q srcVal2 [15:0] $end
$var reg 1 0 used1 $end
$var reg 1 / used2 $end
$upscope $end
$scope module E $end
$var wire 1 ' clk $end
$var wire 4 R destReg [3:0] $end
$var wire 8 S memAddr [7:0] $end
$var wire 16 T memValueLoad [15:0] $end
$var wire 4 U opcode [3:0] $end
$var wire 1 * rst $end
$var wire 16 V srcVal1 [15:0] $end
$var wire 16 W srcVal2 [15:0] $end
$var wire 1 0 used1 $end
$var wire 1 / used2 $end
$var wire 1 + valueReady $end
$var wire 1 2 storeDone $end
$var reg 16 X LastComputedValue [15:0] $end
$var reg 16 Y ProcessorStatusWord [15:0] $end
$var reg 4 Z destRegStore [3:0] $end
$var reg 16 [ destVal [15:0] $end
$var reg 8 \ memAddrLoadStore [7:0] $end
$var reg 16 ] memValueStore [15:0] $end
$var reg 1 # powerdown $end
$var reg 1 " readReq $end
$var reg 1 1 storeNow $end
$var reg 16 ^ val1 [15:0] $end
$var reg 16 _ val2 [15:0] $end
$var reg 1 ! writeReq $end
$upscope $end
$scope module I $end
$var wire 1 ' clk $end
$var wire 16 ` instr [15:0] $end
$var wire 1 * rst $end
$var reg 16 a curr_instr [15:0] $end
$var reg 8 b prog_ctr [7:0] $end
$upscope $end
$scope module R $end
$var wire 1 ' clk $end
$var wire 4 c destReg [3:0] $end
$var wire 16 d destVal [15:0] $end
$var wire 4 e nextDestReg [3:0] $end
$var wire 1 * rst $end
$var wire 4 f srcReg1 [3:0] $end
$var wire 4 g srcReg2 [3:0] $end
$var wire 1 1 storeNow $end
$var reg 1 @ inuse1 $end
$var reg 1 ? inuse2 $end
$var reg 16 h srcRegVal1 [15:0] $end
$var reg 16 i srcRegVal2 [15:0] $end
$var reg 1 2 storeDone $end
$var integer 32 j i [31:0] $end
$upscope $end
$upscope $end
$upscope $end
$enddefinitions $end
#0
$dumpvars
b10000 j
b0 i
b0 h
b0 g
b0 f
b0 e
b0 d
b0 c
b0 b
b0 a
b0 `
b0 _
b0 ^
b0 ]
b0 \
b0 [
b0 Z
b0 Y
b0 X
b0 W
b0 V
b0 U
b0 T
b0 S
b0 R
b0 Q
b0 P
b0 O
b0 N
b0 M
b0 L
b0 K
b0 J
b0 I
b0 H
b0 G
b0 F
b0 E
b0 D
b0 C
b0 B
b0 A
0@
0?
b0 >
b0 =
b0 <
b0 ;
b0 :
b0 9
b0 8
b0 7
b0 6
b0 5
b0 4
b0 3
02
01
00
0/
b0 .
b0 -
b11111111 ,
0+
0*
b0 )
b0 (
0'
b0 &
b0 %
b0 $
0#
0"
x!
$end
#2
b1110100000000001 (
b1110100000000001 -
b1110100000000001 `
b1 &
b1 A
b1 b
b10000 j
0!
1'
#4
0'
#6
b1110100000010010 (
b1110100000010010 -
b1110100000010010 `
b10000 j
b10 &
b10 A
b10 b
b1110100000000001 E
b1110100000000001 I
b1110100000000001 a
1'
#7
1/
10
1?
1@
b1 D
b1 J
b1 R
b1 ;
b1 L
b1 e
b10000000 >
b10000000 K
b10000000 S
b1110 :
b1110 M
b1110 U
#8
12
11
b1 C
b1 Z
b1 c
b1 B
b1 [
b1 d
1+
b1 )
b1 .
b1 T
0"
b10000000 %
b10000000 =
b10000000 \
0'
#9
b1 X
#10
b10001100100001 (
b10001100100001 -
b10001100100001 `
b11 &
b11 A
b11 b
b1110100000010010 E
b1110100000010010 I
b1110100000010010 a
b10000 j
01
1'
#11
0/
00
0?
0@
b10 D
b10 J
b10 R
b10 ;
b10 L
b10 e
b10000001 >
b10000001 K
b10000001 S
#12
12
11
b10 C
b10 Z
b10 c
b10 B
b10 [
b10 d
b10 )
b10 .
b10 T
1+
0"
b10000001 %
b10000001 =
b10000001 \
0'
#13
b10 X
#14
b1111100000100011 (
b1111100000100011 -
b1111100000100011 `
b10000 j
b100 &
b100 A
b100 b
b10001100100001 E
b10001100100001 I
b10001100100001 a
01
1'
#15
10
b1 3
b1 Q
b1 W
b10 4
b10 P
b10 V
1@
b1 5
b1 G
b1 i
b10 6
b10 H
b10 h
b1 7
b1 O
b1 g
b10 8
b10 N
b10 f
b11 D
b11 J
b11 R
b11 ;
b11 L
b11 e
b10 :
b10 M
b10 U
#16
12
11
b11 C
b11 Z
b11 c
b11 B
b11 [
b11 d
b1 _
b10 ^
0'
#17
b11 X
#18
b1110100000000100 (
b1110100000000100 -
b1110100000000100 `
b101 &
b101 A
b101 b
b1111100000100011 E
b1111100000100011 I
b1111100000100011 a
b10000 j
01
1'
#19
b11 4
b11 P
b11 V
b11 6
b11 H
b11 h
b11 8
b11 N
b11 f
b10000010 >
b10000010 K
b10000010 S
b1111 :
b1111 M
b1111 U
#20
1!
b11 $
b11 <
b11 ]
b10000010 %
b10000010 =
b10000010 \
b11 ^
0'
#22
b1110100000010101 (
b1110100000010101 -
b1110100000010101 `
b10000 j
b110 &
b110 A
b110 b
b1110100000000100 E
b1110100000000100 I
b1110100000000100 a
0!
1'
#23
b100 D
b100 J
b100 R
b100 ;
b100 L
b100 e
b10000000 >
b10000000 K
b10000000 S
b1110 :
b1110 M
b1110 U
#24
12
11
b100 C
b100 Z
b100 c
b1 B
b1 [
b1 d
b1 )
b1 .
b1 T
1+
0"
b10000000 %
b10000000 =
b10000000 \
0'
#25
b1 X
#26
b11011001000101 (
b11011001000101 -
b11011001000101 `
b111 &
b111 A
b111 b
b1110100000010101 E
b1110100000010101 I
b1110100000010101 a
b10000 j
01
1'
#27
00
0@
b101 D
b101 J
b101 R
b101 ;
b101 L
b101 e
b10000001 >
b10000001 K
b10000001 S
#28
12
11
b101 C
b101 Z
b101 c
b10 B
b10 [
b10 d
b10 )
b10 .
b10 T
1+
0"
b10000001 %
b10000001 =
b10000001 \
0'
#29
b10 X
#30
b1111100000100110 (
b1111100000100110 -
b1111100000100110 `
b10000 j
b1000 &
b1000 A
b1000 b
b11011001000101 E
b11011001000101 I
b11011001000101 a
01
1'
#31
1/
b10 3
b10 Q
b10 W
b1 4
b1 P
b1 V
1?
b10 5
b10 G
b10 i
b1 6
b1 H
b1 h
b101 7
b101 O
b101 g
b100 8
b100 N
b100 f
b110 D
b110 J
b110 R
b110 ;
b110 L
b110 e
b11 :
b11 M
b11 U
#32
12
11
b110 C
b110 Z
b110 c
b1000000000000000 9
b1000000000000000 Y
b1111111111111111 B
b1111111111111111 [
b1111111111111111 d
b10 _
b1 ^
0'
#33
b1111111111111111 X
#34
b1110100000000111 (
b1110100000000111 -
b1110100000000111 `
b1001 &
b1001 A
b1001 b
b1111100000100110 E
b1111100000100110 I
b1111100000100110 a
b10000 j
b1000000000000000 F
01
1'
#35
0/
10
b1111111111111111 4
b1111111111111111 P
b1111111111111111 V
0?
1@
b1111111111111111 6
b1111111111111111 H
b1111111111111111 h
b110 8
b110 N
b110 f
b10000010 >
b10000010 K
b10000010 S
b1111 :
b1111 M
b1111 U
b0 9
b0 Y
#36
1!
b1111111111111111 $
b1111111111111111 <
b1111111111111111 ]
b10000010 %
b10000010 =
b10000010 \
b1111111111111111 ^
0'
#38
b1110100000011000 (
b1110100000011000 -
b1110100000011000 `
b0 F
b10000 j
b1010 &
b1010 A
b1010 b
b1110100000000111 E
b1110100000000111 I
b1110100000000111 a
0!
1'
#39
b111 D
b111 J
b111 R
b111 ;
b111 L
b111 e
b10000000 >
b10000000 K
b10000000 S
b1110 :
b1110 M
b1110 U
#40
12
11
b111 C
b111 Z
b111 c
b1 B
b1 [
b1 d
b1 )
b1 .
b1 T
1+
0"
b10000000 %
b10000000 =
b10000000 \
0'
#41
b1 X
#42
b100100101111000 (
b100100101111000 -
b100100101111000 `
b1011 &
b1011 A
b1011 b
b1110100000011000 E
b1110100000011000 I
b1110100000011000 a
b10000 j
01
1'
#43
00
0@
b1000 D
b1000 J
b1000 R
b1000 ;
b1000 L
b1000 e
b10000001 >
b10000001 K
b10000001 S
#44
12
11
b1000 C
b1000 Z
b1000 c
b10 B
b10 [
b10 d
b10 )
b10 .
b10 T
1+
0"
b10000001 %
b10000001 =
b10000001 \
0'
#45
b10 X
#46
b1111100000101001 (
b1111100000101001 -
b1111100000101001 `
b10000 j
b1100 &
b1100 A
b1100 b
b100100101111000 E
b100100101111000 I
b100100101111000 a
01
1'
#47
1/
b1 4
b1 P
b1 V
1?
b1 6
b1 H
b1 h
b1000 7
b1000 O
b1000 g
b111 8
b111 N
b111 f
b1001 D
b1001 J
b1001 R
b1001 ;
b1001 L
b1001 e
b100 :
b100 M
b100 U
#48
12
11
b1001 C
b1001 Z
b1001 c
b1 ^
0'
#50
b101100101111000 (
b101100101111000 -
b101100101111000 `
b1101 &
b1101 A
b1101 b
b1111100000101001 E
b1111100000101001 I
b1111100000101001 a
b10000 j
01
1'
#51
0/
10
b10 4
b10 P
b10 V
0?
1@
b10 6
b10 H
b10 h
b1001 8
b1001 N
b1001 f
b10000010 >
b10000010 K
b10000010 S
b1111 :
b1111 M
b1111 U
#52
1!
b10 $
b10 <
b10 ]
b10000010 %
b10000010 =
b10000010 \
b10 ^
0'
#54
b1111100000101001 (
b1111100000101001 -
b1111100000101001 `
b10000 j
b1110 &
b1110 A
b1110 b
b101100101111000 E
b101100101111000 I
b101100101111000 a
0!
1'
#55
00
b1 4
b1 P
b1 V
0@
b1 6
b1 H
b1 h
b111 8
b111 N
b111 f
b101 :
b101 M
b101 U
#56
12
11
b100 B
b100 [
b100 d
b1 ^
0'
#57
b100 X
#58
b110100101111000 (
b110100101111000 -
b110100101111000 `
b1111 &
b1111 A
b1111 b
b1111100000101001 E
b1111100000101001 I
b1111100000101001 a
b10000 j
01
1'
#59
10
b100 4
b100 P
b100 V
1@
b100 6
b100 H
b100 h
b1001 8
b1001 N
b1001 f
b1111 :
b1111 M
b1111 U
#60
1!
b100 $
b100 <
b100 ]
b100 ^
0'
#62
b1111100000101001 (
b1111100000101001 -
b1111100000101001 `
b10000 j
b10000 &
b10000 A
b10000 b
b110100101111000 E
b110100101111000 I
b110100101111000 a
0!
1'
#63
00
b1 4
b1 P
b1 V
0@
b1 6
b1 H
b1 h
b111 8
b111 N
b111 f
b110 :
b110 M
b110 U
#64
12
b10000000000000 9
b10000000000000 Y
11
b0 B
b0 [
b0 d
b1 ^
0'
#65
b0 X
#66
b111100101111000 (
b111100101111000 -
b111100101111000 `
b10001 &
b10001 A
b10001 b
b1111100000101001 E
b1111100000101001 I
b1111100000101001 a
b10000 j
b10000000000000 F
01
1'
#67
10
b0 4
b0 P
b0 V
1@
b0 6
b0 H
b0 h
b1001 8
b1001 N
b1001 f
b1111 :
b1111 M
b1111 U
b0 9
b0 Y
#68
1!
b0 $
b0 <
b0 ]
b0 ^
0'
#70
b1111100000101001 (
b1111100000101001 -
b1111100000101001 `
b0 F
b10000 j
b10010 &
b10010 A
b10010 b
b111100101111000 E
b111100101111000 I
b111100101111000 a
0!
1'
#71
00
b1 4
b1 P
b1 V
0@
b1 6
b1 H
b1 h
b111 8
b111 N
b111 f
b111 :
b111 M
b111 U
#72
12
b10000000000000 9
b10000000000000 Y
11
b1 ^
0'
#74
b1000100101111000 (
b1000100101111000 -
b1000100101111000 `
b10011 &
b10011 A
b10011 b
b1111100000101001 E
b1111100000101001 I
b1111100000101001 a
b10000 j
b10000000000000 F
01
1'
#75
10
b0 4
b0 P
b0 V
1@
b0 6
b0 H
b0 h
b1001 8
b1001 N
b1001 f
b1111 :
b1111 M
b1111 U
b0 9
b0 Y
#76
1!
b0 ^
0'
#78
b1111100000101001 (
b1111100000101001 -
b1111100000101001 `
b0 F
b10000 j
b10100 &
b10100 A
b10100 b
b1000100101111000 E
b1000100101111000 I
b1000100101111000 a
0!
1'
#79
00
b1 4
b1 P
b1 V
0@
b1 6
b1 H
b1 h
b111 8
b111 N
b111 f
b1000 :
b1000 M
b1000 U
#80
12
11
b11 B
b11 [
b11 d
b1 ^
0'
#81
b11 X
#82
b1001100101111000 (
b1001100101111000 -
b1001100101111000 `
b10101 &
b10101 A
b10101 b
b1111100000101001 E
b1111100000101001 I
b1111100000101001 a
b10000 j
01
1'
#83
10
b11 4
b11 P
b11 V
1@
b11 6
b11 H
b11 h
b1001 8
b1001 N
b1001 f
b1111 :
b1111 M
b1111 U
#84
1!
b11 $
b11 <
b11 ]
b11 ^
0'
#86
b1111100000101001 (
b1111100000101001 -
b1111100000101001 `
b10000 j
b10110 &
b10110 A
b10110 b
b1001100101111000 E
b1001100101111000 I
b1001100101111000 a
0!
1'
#87
00
b1 4
b1 P
b1 V
0@
b1 6
b1 H
b1 h
b111 8
b111 N
b111 f
b1001 :
b1001 M
b1001 U
#88
12
11
b1111111111111110 B
b1111111111111110 [
b1111111111111110 d
b1 ^
0'
#89
b1111111111111110 X
#90
b1010100101111000 (
b1010100101111000 -
b1010100101111000 `
b10111 &
b10111 A
b10111 b
b1111100000101001 E
b1111100000101001 I
b1111100000101001 a
b10000 j
01
1'
#91
10
b1111111111111110 4
b1111111111111110 P
b1111111111111110 V
1@
b1111111111111110 6
b1111111111111110 H
b1111111111111110 h
b1001 8
b1001 N
b1001 f
b1111 :
b1111 M
b1111 U
